{"Clouds": {"crafted_by": [["Geysers", "Wind"]], "depth": 5}, "Ice Cowboy": {"crafted_by": [["Ice Dragon", "Space Cowboy"]], "depth": 5}, "Landslide": {"crafted_by": [["Earth", "Avalanche"], ["Earth", "Mudslide"], ["Avalanche", "Mudslide"], ["Soil", "Earthquake"], ["Earthquake", "Mudslide"], ["Wreck", "Mountain Dirt"], ["Sandwichlandslide", "Earth"], ["Crush", "Earth"], ["Earth", "Mountain Slide"], ["Earth", "Stealthlandslide"], ["Mark Twain", "Mountain Slide"], ["Mountain Dirt", "Truck"], ["Mountain Dirt", "Accident"], ["Mountain Dirt", "Fall"], ["Mountain Dirt", "Typhoon"], ["Mountain Dirt", "Mudslide"], ["Mountain Dirt", "Crash"]], "depth": 3}, "Salmon": {"crafted_by": [["Salt", "Norway"], ["Salt", "River"], ["Mountain Range", "Fish"], ["Fjord", "Fish"], ["Fjord", "Sushi"], ["Fish", "Norway"], ["Fish", "Forest"], ["Fish", "Honey"], ["Fish", "River"], ["Norway", "Sushi"], ["Norway", "Kelp"], ["Sushi", "River"], ["Dragon", "Rainbow Trout"], ["Steamship", "Rainbow Trout"], ["Party", "Rainbow Trout"], ["Salad", "Chinook"], ["Salad", "Aquavit"], ["Salad", "Siren"], ["Salad", "Fjord"], ["Salad", "Sperm"], ["Salad", "Smell"], ["Salad", "Ice Fishing"], ["Salad", "Noah"], ["Salad", "Sushi"], ["Salad", "Norway"], ["Salad", "Lake"], ["Salad", "Lagoon"], ["Salad", "Skimming"], ["Salad", "Steam Norway"], ["Salad", "Rainbow Trout"], ["Salad", "Log"], ["Salad", "River"], ["Salad", "Flood"], ["Salad", "Oslo"], ["Salad", "Eskimo"], ["Salad", "Smoking"], ["Salad", "Sea"], ["Salad", "Jonah"], ["Sandwich", "Salamander"], ["Chinook", "Fire"], ["Fire", "Rainbow Trout"], ["Earth", "Rainbow Trout"], ["Chinook", "Water"], ["Boston Tea Party", "Rainbow Trout"], ["Mire", "Rainbow Trout"], ["Chinook", "Soup"], ["Chinook", "Eel"], ["Chinook", "Smoke"], ["Chinook", "Survivor"], ["Chinook", "Sushi Boat"], ["Chinook", "Poke"], ["Chinook", "Mermaid"], ["Chinook", "Lily"], ["Chinook", "Pisces"], ["Chinook", "Vulcan"], ["Chinook", "Nymph"], ["Chinook", "Wine"], ["Chinook", "Sunk"], ["Chinook", "Fish"], ["Chinook", "Seasick"], ["Chinook", "Love Boat"], ["Chinook", "Salamander"], ["Chinook", "Bridge"], ["Chinook", "Smoker"], ["Chinook", "Lung"], ["Chinook", "Snake Trap"], ["Chinook", "Goldfish"], ["Chinook", "Something"], ["Chinook", "Pufferfish"], ["Chinook", "Pink"], ["Chinook", "Boat"], ["Chinook", "Vinegar"], ["Chinook", "Reef"], ["Chinook", "Archipelago"], ["Chinook", "Swordfish"], ["Chinook", "Algae"], ["Chinook", "Aloe"], ["Chinook", "Palm Oil"], ["Chinook", "Miracle"], ["Chinook", "Sink"], ["Chinook", "Sperm"], ["Chinook", "Stew"], ["Chinook", "Driftwood"], ["Chinook", "Smell"], ["Chinook", "Pickle"], ["Chinook", "Dandelion Tea"], ["Chinook", "Splash"], ["Chinook", "Mountain Oasis"], ["Chinook", "Shore"], ["Chinook", "Pelican"], ["Chinook", "Popcorn"], ["Chinook", "Salty"], ["Chinook", "Krill"], ["Chinook", "Water Lily"], ["Chinook", "Seaplane"], ["Chinook", "Fisherman"], ["Chinook", "SOS"], ["Chinook", "Ocean"], ["Chinook", "Raft"], ["Chinook", "Norway"], ["Chinook", "Fall"], ["Chinook", "Naiad"], ["Chinook", "Dock"], ["Chinook", "Rainforest"], ["Chinook", "Big Dipper"], ["Chinook", "Sushi"], ["Chinook", "Scent"], ["Chinook", "Sting"], ["Chinook", "Leaf"], ["Chinook", "Lake"], ["Chinook", "Fruit"], ["Chinook", "Blessing"], ["Chinook", "Oil"], ["Chinook", "Tears"], ["Chinook", "Life"], ["Chinook", "Lagoon"], ["Chinook", "Skimming"], ["Chinook", "Sake"], ["Chinook", "Flatfish"], ["Chinook", "Mountain Sushi"], ["Chinook", "Kiln"], ["Chinook", "Rainbow Trout"], ["Chinook", "Dust Fish"], ["Chinook", "Coral Reef"], ["Chinook", "Muddy Sushi"], ["Chinook", "River"], ["Chinook", "Saltwater"], ["Chinook", "Honeymoon"], ["Chinook", "Soggy"], ["Chinook", "Tide"], ["Chinook", "Watermelon"], ["Chinook", "Snowfish"], ["Chinook", "Table"], ["Chinook", "Tear"], ["Chinook", "Beefish"], ["Chinook", "Steamfish"], ["Chinook", "Date"], ["Chinook", "Mudskipper"], ["Chinook", "Umami"], ["Chinook", "Sushitic"], ["Chinook", "Surf and Turf"], ["Chinook", "Flood"], ["Chinook", "Wishbone"], ["Chinook", "Carp"], ["Chinook", "Nile"], ["Chinook", "Ice Fish"], ["Chinook", "Poison"], ["Chinook", "Wet"], ["Chinook", "Hot Spring"], ["Chinook", "Knife"], ["Chinook", "Muddy"], ["Chinook", "Spring"], ["Chinook", "Sea"], ["Chinook", "Pond"], ["Chinook", "Waterfall"], ["Chinook", "Ganges"], ["Chinook", "Smoking"], ["Chinook", "Sacrifice"], ["Chinook", "Koi"], ["Chinook", "Ferry"], ["Chinook", "Grinder"], ["Mountain Venus", "Rainbow Trout"], ["Rainbow Fish", "Forest Fire"], ["Rainbow Fish", "Fjord"], ["Rainbow Fish", "Autumn"], ["Rainbow Fish", "Bear"], ["Rainbow Fish", "Norway"], ["Rainbow Fish", "Forest"], ["Rainbow Fish", "Steam Norway"], ["Rainbow Fish", "Mountain Steam"], ["Mountain Dirt", "Rainbow Trout"]], "depth": 4}, "Calamari": {"crafted_by": [["Party", "Squid"], ["Sandwich", "Kraken"], ["Fire", "Squid"], ["Salad", "Kraken"], ["Salad", "Squid"], ["Sandwich", "Squid"]], "depth": 5}, "Coughing Tea Party": {"crafted_by": [["Coughing", "Dust Tea Party"]], "depth": 5}, "Hula-Dragon": {"crafted_by": [["Dragon", "Hula"]], "depth": 5}, "Thief": {"crafted_by": [["Stealth", "Diamond"], ["Stealth", "Goblin"], ["Stealth", "Ring"], ["Stealth", "Night"], ["Stealth", "Money"], ["Stealth", "Gnome"], ["Stealth", "Treasure"], ["Stealth", "Mercury"], ["Stealth", "Dwarf"], ["Fire", "Sneaky"], ["Earth", "Sneaky"], ["Sandal", "Lightbulb"], ["Sandal", "Shaman"], ["Sandal", "Phoenix Palm"], ["Sandal", "Moon Dew"], ["Sandal", "Magnifying Glass"], ["Sandal", "Light Bulb"], ["Sandal", "Jack"], ["Sandal", "Black Lily"]], "depth": 5}, "Tea Davidson": {"crafted_by": [["Tea Ceremony", "David"], ["Tea Davidson", "Water"]], "depth": 5}, "Dandelion": {"crafted_by": [["Wind", "Plant"], ["Lily", "Dust Storm"], ["Mangrove", "Dandelion"], ["Mangrove", "Dandelion Patch"], ["Landslide", "Dandelion Patch"], ["Salt", "Dandelion"], ["Salt", "Dandelion Patch"], ["Volcano", "Dandelion Patch"], ["Dust Devil", "Lily"], ["Dust Bunny", "Flower"], ["Lily", "Dust Bowl"], ["Dandelion", "Dandelion Patch"], ["Dandelion", "Atlantis"], ["Dandelion", "Buddha"], ["Dandelion", "Wish"], ["Dandelion", "Troll"], ["Dandelion", "Plantea"], ["Perfume", "Dandelion Patch"], ["Tornado", "Dandelion Patch"], ["Destruction", "Dandelion Patch"], ["Fog", "Dandelion Patch"], ["Venus", "Dandelion Patch"], ["Continent", "Dandelion Patch"], ["Storm", "Dandelion Patch"], ["Obsidian", "Dandelion Patch"], ["Viking", "Dandelion Patch"], ["Dandelion Patch", "Pollen"], ["Dandelion Patch", "Iceland"], ["Dandelion Patch", "Steamboat"], ["Dandelion Patch", "Thunder"], ["Dandelion Patch", "Atlantis"], ["Dandelion Patch", "Nothing"], ["Dandelion Patch", "Geyser"], ["Dandelion Patch", "Sky"], ["Dandelion Patch", "Buddha"], ["Dandelion Patch", "Wave"], ["Dandelion Patch", "Mist"], ["Dandelion Patch", "Sandbox"], ["Dandelion Patch", "Clay"], ["Dandelion Patch", "Seed"], ["Dandelion Patch", "Weed"], ["Dandelion Patch", "Earthquake"], ["Dandelion Patch", "Mountain Dew"], ["Dandelion Patch", "Puddle"], ["Dandelion Patch", "Soil"], ["Dandelion Patch", "Sushi"], ["Dandelion Patch", "Wish"], ["Dandelion Patch", "Train"], ["Dandelion Patch", "Leaf"], ["Dandelion Patch", "Pencil"], ["Dandelion Patch", "Lagoon"], ["Dandelion Patch", "Mushroom"], ["Dandelion Patch", "Mudweed"], ["Dandelion Patch", "Forest"], ["Dandelion Patch", "Plantea"], ["Dandelion Patch", "Sandalwood"], ["Dandelion Patch", "Troll"], ["Dandelion Patch", "Flower"], ["Dandelion Patch", "Shipwreck"], ["Dandelion Patch", "Plant"], ["Dandelion Patch", "Water"], ["Dandelion Patch", "Lotus"], ["Dandelion Patch", "Tempest"], ["Dandelion Patch", "Sandcastle"], ["Pollen", "Cactus"], ["Saturn", "Flower"], ["Seed", "Kite"], ["Seed", "Wind"], ["Flower", "Wind"], ["Flower", "Sandcastle"], ["Flower", "Cyclone"], ["Flower", "Dust Bowl"], ["Earth", "Dandelion Patch"], ["Stealth", "Dandelion Patch"], ["Wreck", "Dandelion Sandwich"], ["Wreck", "Dandelion"], ["Wreck", "Dandelion Wine"], ["Wreck", "Dandelion Patch"], ["Salad", "Dust Weed"], ["Poppy", "Wind"], ["Herbivore", "Wind"], ["Dandelion Sandwich", "Earth"], ["Fossilized Dandelion", "Wind"], ["Earth", "Dandelion Wine"], ["Earth", "Dandelion Tea"], ["Earth", "Dandelion Island"], ["Earth", "Dandelion Roll"], ["Earth", "Sneezeweed"], ["Dandelion Tea", "Wind"], ["Wet Dandelion Patch", "Wind"], ["Flower Crown", "Wind"], ["Dandelion Soup", "Wind"], ["Steamship", "Dandelion Patch"], ["Party", "Dandelion Sandwich"], ["Wreck", "Dandelion Tea"], ["Moana", "Dandelion"], ["Mire", "Dandelion Sandwich"], ["Mire", "Dandelion Wine"], ["Mire", "Dandelion Tea"], ["Ghost", "Dandelion Tea"], ["Paddle", "Wet Dandelion Patch"], ["Cougher", "Seedpod"], ["Chinook", "Dandelion Wine"], ["Steam Forest", "Dandelion Sandwich"], ["Steam Forest", "Dandelion Tea"], ["Mountain Venus", "Dandelion Sandwich"], ["Mountain Venus", "Dandelion"], ["Mountain Venus", "Dandelion Wine"], ["Mountain Venus", "Dandelion Patch"], ["Mountain Venus", "Dandelion Tea"], ["Mountain Dirt", "Dandelion Wine"], ["Mountain Dirt", "Dandelion Patch"], ["Mountain Dirt", "Dandelion Tea"], ["Mountain Dirt", "Dandelion Roll"], ["Cleaner", "Dandelion"]], "depth": 2}, "Lawrence Of Arabia": {"crafted_by": [["Party", "Lawrence of Arabia"], ["Ghost", "Lawrence of Arabia"]], "depth": 5}, "Duck Dirt": {"crafted_by": [["Mountain Dirt", "Duck"]], "depth": 5}, "Thumb": {"crafted_by": [["Sandal", "Palm"], ["Sandal", "Carnation"], ["Sandal", "Big Dipper"]], "depth": 5}, "Geothermal": {"crafted_by": [["Volcano", "Windmill"], ["Windmill", "Yellowstone"], ["Windmill", "Lava"], ["Palm Tree", "Yellowstone"], ["Steam", "Rock"], ["Yellowstone", "Soil"], ["Yellowstone", "Kelp"], ["Mountain Venus", "Steam"]], "depth": 4}, "Titanosaur": {"crafted_by": [["Fossil", "Titan"]], "depth": 5}, "Bumble Ness": {"crafted_by": [["Loch Ness Monster", "Bumblebee"]], "depth": 5}, "Grind Wreck": {"crafted_by": [["Wreck", "Grinder"]], "depth": 5}, "Yakisoba Pan": {"crafted_by": [["Yakisoba", "Wind"]], "depth": 6}, "Sink Twain": {"crafted_by": [["Mark Twain", "Sink"], ["Mark Twain", "Sinkhole"]], "depth": 5}, "Fire Rocket": {"crafted_by": [["Fire", "Salad Rocket"], ["Fire Breath", "Snow Rocket"]], "depth": 5}, "Tire Swing": {"crafted_by": [["Steam Forest", "Tire"]], "depth": 5}, "Matcha Cough": {"crafted_by": [["Coughing", "Matcha Latte"], ["Coughing", "Matcha Tea"]], "depth": 5}, "Pop Tart": {"crafted_by": [["Star", "Toast"]], "depth": 5}, "Grindr": {"crafted_by": [["Mountain Venus", "Grinder"]], "depth": 5}, "Soggy Monkey": {"crafted_by": [["Sandwich Monkey", "Water"]], "depth": 6}, "Amber Stealth": {"crafted_by": [["Stealth", "Amber Alert"], ["Amber Stealth", "Wind"]], "depth": 5}, "Frankenstorm": {"crafted_by": [["Frankenstein", "Wind"]], "depth": 5}, "Lung Cancer": {"crafted_by": [["Palm Tree", "Smog"], ["Star", "Lung Cancer"], ["Cougher", "Smoker"], ["Cougher", "Cigarette"], ["Coughland", "Cigarette"], ["Coughland", "Smoking"], ["Coughing", "Tobacco"], ["Coughing", "Smoker"], ["Coughing", "Bong"], ["Coughing", "Don Quixote"], ["Coughing", "Cigarette"], ["Coughing", "Smoking"]], "depth": 4}, "Soggy Sandwich": {"crafted_by": [["Sandwich", "Bogland"], ["Sandwich Roll", "Water"], ["Black Sandwich", "Water"], ["Christmas Sandwich", "Water"], ["Sandwichman", "Water"], ["Ham Sandwich", "Water"], ["Hot Sandwich", "Water"], ["Soggy Sandwich", "Water"], ["Sandwich Tempest", "Water"], ["Open Faced Sandwich", "Water"], ["Space Sandwich", "Water"], ["Flying Sandwich", "Water"], ["Egg Salad Sandwich", "Water"]], "depth": 5}, "Calendar": {"crafted_by": [["Star", "Date"], ["Fire", "Mayan"], ["Year", "Water"]], "depth": 5}, "Picnic": {"crafted_by": [["Sandwich", "Wine"], ["Sandwich", "Forest"], ["Sandwich", "Wood"], ["Party", "Park"], ["Salad", "Bear"], ["Salad", "Park"], ["Salad", "Woodpecker"], ["Sandwich", "Tea Table"], ["Sandwich", "Field"], ["Sandwich", "Sunstroke"], ["Sandwich", "Sunset"], ["Sandwich", "Vacation"], ["Sandwich", "Park"], ["Sandwich", "Sangria"], ["Sandwich", "Table"], ["Sandwich", "Crayon"], ["Sandwich", "Lawnmower"], ["Sandwich", "Tourist"], ["Sandwich", "Vinegar"], ["Sandwich", "Bear"], ["Sandwich", "Sun Tea"], ["Sandwich", "Mountain Wine"], ["Sandwich", "Hayride"], ["Sandwich", "Trees"], ["Sandwich", "Lawn"], ["Sandwich", "Sketch"], ["Sandwich", "Woodchips"], ["Sandwich", "Sunshine"], ["Sandwich", "Sunflower"], ["Sandwich", "Map"], ["Sandwich", "Woodpecker"]], "depth": 4}, "Pickled Dragon Egg": {"crafted_by": [["Dragon Egg", "Vinegar"]], "depth": 5}, "Sandal Trap": {"crafted_by": [["Sandal", "Sand Trap"]], "depth": 5}, "Sick": {"crafted_by": [["Steamship", "Seasick"], ["Sandwich", "Cough Syrup"], ["Pneumonia", "Water"], ["Virus", "Water"], ["Ghost", "Malaria"], ["Cougher", "Tea Whale"], ["Cougher", "Sunstroke"], ["Cougher", "Acid Rain"], ["Cougher", "Green"], ["Cougher", "Muddy Sushi"], ["Cougher", "Mars Bar"], ["Cougher", "Sneezy"], ["Coughland", "Sneezy"], ["Coughing", "Tea Whale"], ["Coughing", "Statue of Liberty"], ["Coughing", "Green"], ["Coughing", "Frozen"], ["Coughing", "Greenland"], ["Coughing", "Yin Yang"], ["Coughing", "Muddy Sushi"], ["Coughing", "Ice Snake"], ["Coughing", "Asia"], ["Coughing", "Sneezy"]], "depth": 5}, "Boomland": {"crafted_by": [["Coughland", "Boom"]], "depth": 5}, "Party Bear": {"crafted_by": [["Party", "Polar Bear"]], "depth": 5}, "Michelangelo": {"crafted_by": [["Cleaner", "Sculpture"]], "depth": 5}, "Who": {"crafted_by": [["Mark Twain", "Owl"]], "depth": 5}, "Lotus Mountain": {"crafted_by": [["Mountain Venus", "Lotus Flower"]], "depth": 5}, "Swamp Thing": {"crafted_by": [["Titanic", "Swamp"], ["Swamp", "Venus Flytrap"], ["Stealth", "Swampmobile"], ["Wreck", "Swamp Thing"], ["Wreck", "Swampmobile"], ["Salad", "Swampmobile"], ["Salad", "Muddy Helicopter"], ["Star", "Swamp Thing"], ["Swamp Thing", "Wind"], ["Sandal", "Swamp Thing"], ["Sandal", "Swampmobile"], ["Cougher", "Swampmobile"], ["Chinook", "Swamp Thing"], ["Coughland", "Swampmobile"], ["Mountain Venus", "Swampmobile"], ["Coughing", "Swampmobile"]], "depth": 4}, "Rocky Wreck": {"crafted_by": [["Wreck", "Rocky Mountains"]], "depth": 5}, "Mountain Goat": {"crafted_by": [["Mountain Venus", "Salt Lick"]], "depth": 5}, "Evil Queen": {"crafted_by": [["Fire", "Poison Apple"]], "depth": 6}, "Geysers": {"crafted_by": [["Poseidon", "Yellowstone"], ["Fog", "Yellowstone"], ["Yellowstone", "Swamp"], ["Yellowstone", "Mist"], ["Yellowstone", "Rain"], ["Yellowstone", "Whale"], ["Yellowstone", "Wind"], ["Yellowstone", "Water"], ["Yellowstone", "Oasis"], ["Steam Forest", "Yellowstone"], ["Coughing", "Hot Spring"]], "depth": 4}, "Rainbow Fishstick": {"crafted_by": [["Rainbow Fish", "Fishstick"]], "depth": 5}, "Vegetarian": {"crafted_by": [["Mark Twain", "Carnivore"], ["Mark Twain", "Carrot"]], "depth": 5}, "Hot Cocoa": {"crafted_by": [["Coughing", "Hot Chocolate"]], "depth": 5}, "Rain Man": {"crafted_by": [["Stealth", "Dustin Hoffman"], ["Steamship", "Dustin Hoffman"], ["Party", "Dustin Hoffman"], ["Wreck", "Dustin Hoffman"], ["Salad", "Dustin Hoffman"], ["Fire", "Dustin Hoffman"], ["Earth", "Dustin Hoffman"], ["Dustin Hoffman", "Wind"], ["Dustin Hoffman", "Water"], ["Tea Ceremony", "Dustin Hoffman"], ["Loch Ness Monster", "Dustin Hoffman"], ["Boston Tea Party", "Dustin Hoffman"], ["Star", "Dustin Hoffman"], ["Flying Car", "Dustin Hoffman"], ["Mire", "Dustin Hoffman"], ["Ghost", "Dustin Hoffman"], ["Sandwich", "Dustin Hoffman"], ["Paddle", "Dustin Hoffman"], ["Cougher", "Dustin Hoffman"], ["Coughland", "Dustin Hoffman"], ["Coughing", "Dustin Hoffman"], ["Rainbow Fish", "Dustin Hoffman"], ["Mountain Dirt", "Dustin Hoffman"]], "depth": 5}, "Southern Belle": {"crafted_by": [["Tea Ceremony", "Grits"]], "depth": 5}, "Tea Tide": {"crafted_by": [["Tea Ceremony", "Tide"], ["Tea Devil", "Tide"]], "depth": 5}, "Party Train": {"crafted_by": [["Party", "Tea Train"]], "depth": 5}, "Fasting": {"crafted_by": [["Ramadan", "Earth"], ["Ramadan", "Water"]], "depth": 6}, "Satire": {"crafted_by": [["Mark Twain", "Myth"]], "depth": 5}, "Steam Zombie": {"crafted_by": [["Steam Forest", "Zombie"]], "depth": 5}, "Ectoplasm": {"crafted_by": [["Ghost", "Steam Tea"], ["Ghost", "Mass"]], "depth": 5}, "Jormungandmark": {"crafted_by": [["Mark Twain", "Jormungandr"]], "depth": 5}, "Ice Cream Sandwich": {"crafted_by": [["Sandwich", "Ice"], ["Sandwich", "Ice Dragon"], ["Sandwich", "Snow Dragon"], ["Sandwich", "Funnel Cake"], ["Sandwich", "Snow Cone"], ["Sandwich", "Ice Trap"], ["Sandwich", "Popsicle"], ["Sandwich", "Ice Angel"], ["Sandwich", "Ice Snake"], ["Sandwich", "Frost"], ["Sandwich", "Ice Wine"], ["Sandwich", "Ice Storm"], ["Ice Sandwich", "Water"], ["Sandwich", "Ice Lily"], ["Sandwich", "Frozen"], ["Sandwich", "Ice Train"], ["Sandal", "Ice Sandwich"], ["Sandal", "Ice Trap"], ["Sandal", "Ice Tea"], ["Mire", "Ice Cream Sandwich"], ["Mark Twain", "Ice Cream Sandwich"], ["Sandwich", "Snowcone"], ["Sandwich", "Ice Castle"], ["Sandwich", "Cool"], ["Paddle", "Ice Cream Sandwich"], ["Ice Dragon", "Sandwich Trap"], ["Ice Dragon", "Space Sandwich"], ["Ice Dragon", "Panini"], ["Tea Devil", "Ice Cream Sandwich"]], "depth": 4}, "Cat": {"crafted_by": [["Dust Bunny", "Sphinx"], ["Fossil", "Catnip"], ["Dragon", "Catnip"], ["Steamship", "Catnip"], ["Tea Ceremony", "Catnip"], ["Loch Ness Monster", "Catnip"], ["Wreck", "Catnip"], ["Salad", "Cattail"], ["Salad", "Catnip"], ["Sandwich", "Catnip"], ["Fire", "Catnip"], ["Earth", "Catwreck"], ["Earth", "Cat Party"], ["Earth", "Catnip"], ["Earth", "Catfish"], ["Catnip", "Wind"], ["Cougar", "Water"], ["Party", "Cattail"], ["Star", "Catnip"], ["Flying Car", "Catnip"], ["Moana", "Catnip"], ["Sandal", "Catnip"], ["Mire", "Catnip"], ["Ghost", "Catnip"], ["Paddle", "Catnip"], ["Chinook", "Catnip"], ["Steam Forest", "Catnip"], ["Mountain Venus", "Catnip"], ["Coughing", "Catnip"], ["Tea Devil", "Catnip"], ["Mountain Dirt", "Catnip"]], "depth": 4}, "Vanilla Ice": {"crafted_by": [["Mark Twain", "Icecream"]], "depth": 5}, "Tut Twain": {"crafted_by": [["Mark Twain", "Mummy"]], "depth": 5}, "Steam Buggy": {"crafted_by": [["Steam Forest", "Moon Buggy"], ["Steam Forest", "Dune Buggy"]], "depth": 5}, "Star Wars: The Phantom Menace": {"crafted_by": [["Wreck", "Star Wars"]], "depth": 5}, "Flying Firefighter": {"crafted_by": [["Flying Car", "Firefighter"]], "depth": 5}, "Caladragon": {"crafted_by": [["Dragon", "Calla"]], "depth": 5}, "Hula Hoop": {"crafted_by": [["Sandwich", "Hula"], ["Star", "Hula"], ["Hula", "Water"], ["Mire", "Hula"], ["Chinook", "Hula"], ["Chinook", "Hawaiian Jet"], ["Mountain Venus", "Hula"], ["Coughing", "Hula"]], "depth": 5}, "Infernape": {"crafted_by": [["Fire", "Swampert"]], "depth": 6}, "Jetsam": {"crafted_by": [["Mire", "Jet"]], "depth": 5}, "Sandalphon": {"crafted_by": [["Sandal", "Steam Angel"], ["Sandal", "Angel Flytrap"], ["Sandal", "Angel of Death"], ["Sandal", "Sand Dragon"], ["Sandal", "Dust Nymph"], ["Sandal", "Steam Dragon"], ["Sandal", "Subphoenix"], ["Sandal", "Snow Phoenix"]], "depth": 5}, "Root Beer": {"crafted_by": [["Chinook", "Soda"]], "depth": 5}, "Hacker": {"crafted_by": [["Stealth", "Hack"], ["Party", "Hack"], ["Star", "Hack"], ["Fire", "Hack"], ["Earth", "Hack"], ["Ghost", "Hack"], ["Cougher", "Stoner"], ["Cougher", "Hack"], ["Cougher", "Minecraft"], ["Cougher", "Cool"], ["Cougher", "Choppy"], ["Cougher", "Satellite"]], "depth": 5}, "Sandpunk": {"crafted_by": [["Sandwich", "Steampunk"], ["Sand", "Steampunk"], ["Steampunk", "Sandbox"], ["Fossil", "Sandpunk"], ["Steamship", "Sandpunk"], ["Steam Forest", "Sandpunk"], ["Mountain Venus", "Sandpunk"], ["Rainbow Fish", "Sandpunk"]], "depth": 4}, "Sandcough": {"crafted_by": [["Cougher", "Sandcastle"]], "depth": 5}, "Katana": {"crafted_by": [["Fire", "Samurai"]], "depth": 6}, "Tea Cup": {"crafted_by": [["Helicopter", "Tea Bag"], ["Helicopter", "Tea Storm"], ["Dust Devil", "Tea Party"], ["Tornado", "Tea Bag"], ["Tea Bag", "Cyclone"], ["Tea Party", "Hurricane"], ["Tea", "Venus Flytrap"], ["Tea Ceremony", "Tornado"], ["Wreck", "Tea Pot"], ["Boston Tea Party", "Whirlpool"], ["Boston Tea Party", "Cyclone"], ["Boston Tea Party", "Shatter"], ["Tea Table", "Wind"], ["Tea Urn", "Wind"], ["Tea Shuttle", "Wind"], ["Tea Vacuum", "Wind"], ["Tea Buggy", "Wind"], ["Tea Meteor", "Wind"], ["Tea Truck", "Wind"], ["Tea Station", "Wind"], ["Tea Cobra", "Wind"], ["Tea Car", "Wind"], ["Tea Ceremony", "Shatter"], ["Flying Car", "Tea Pot"], ["Paddle", "Chai Tea"]], "depth": 4}, "Caravan": {"crafted_by": [["Sandal", "Camel"], ["Mire", "Camel"], ["Paddle", "Camel"]], "depth": 5}, "Vinaigrette": {"crafted_by": [["Salad", "Vinegar"], ["Star", "Vinegar"], ["Salad", "Winepress"], ["Coughing", "Vinegar"]], "depth": 5}, "Tea Sanding": {"crafted_by": [["Boston Tea Party", "Sandboarding"]], "depth": 5}, "Coughing Titanic Flytrap": {"crafted_by": [["Cougher", "Titanic Flytrap"]], "depth": 5}, "Sandstar": {"crafted_by": [["Star", "Sandvik"]], "depth": 5}, "Barrel": {"crafted_by": [["Wine", "Wood"]], "depth": 4}, "Rainbow Drone": {"crafted_by": [["Rainbow Fish", "Drone"]], "depth": 5}, "Cremation": {"crafted_by": [["Fire", "Funeral"]], "depth": 6}, "Sandpiercer": {"crafted_by": [["Sandwich", "Snowpiercer"], ["Sandpiercer", "Water"]], "depth": 5}, "Flying Dust Buster": {"crafted_by": [["Flying Car", "Dust Buster"]], "depth": 5}, "Windsurf": {"crafted_by": [["Chinook", "Surf"]], "depth": 5}, "Smuggler": {"crafted_by": [["Stealth", "Cargo"]], "depth": 5}, "Landfill": {"crafted_by": [["Garbage", "Earth"], ["Earth", "Junkyard"], ["Earth", "Barrel"], ["Earth", "Dustbin"], ["Earth", "Trash"], ["Earth", "Junk"], ["Earth", "Salvage"], ["Earth", "Waste"], ["Earth", "Fridge"], ["Mountain Dirt", "Dustbin"]], "depth": 5}, "Karate": {"crafted_by": [["Tea Ceremony", "Choke"], ["Jackie Chan", "Water"], ["Tea Ceremony", "Punch"]], "depth": 5}, "Mistaken Identity": {"crafted_by": [["Mark Twain", "Mirage"]], "depth": 5}, "Frost Ammonite": {"crafted_by": [["Ice Dragon", "Ammonite"]], "depth": 5}, "Ninja Fruit": {"crafted_by": [["Stealth", "Dragon Fruit"]], "depth": 5}, "Flying Cannon": {"crafted_by": [["Flying Car", "Cannon"]], "depth": 5}, "Cartoon": {"crafted_by": [["Party", "Sketch"]], "depth": 5}, "Puncture": {"crafted_by": [["Earth", "Flat Tire"]], "depth": 6}, "Salad Tornado": {"crafted_by": [["Salad Train", "Wind"], ["Salad Tornado", "Water"]], "depth": 6}, "Hot Chinook": {"crafted_by": [["Chinook", "Hot Chocolate"]], "depth": 5}, "Mount Olympus": {"crafted_by": [["Mountain Venus", "Saint"], ["Mountain Venus", "Prison"], ["Mountain Venus", "Mountain Range"], ["Mountain Venus", "Pot Brownie"], ["Mountain Venus", "Los Angeles"], ["Mountain Venus", "Paradise"], ["Mountain Venus", "Europe"], ["Mountain Venus", "Continent"], ["Mountain Venus", "Ring"], ["Mountain Venus", "High"], ["Mountain Venus", "Kraken"], ["Mountain Venus", "Antarctica"], ["Mountain Venus", "Haunted House"], ["Mountain Venus", "Pancake"], ["Mountain Venus", "Seaplane"], ["Mountain Venus", "Temple"], ["Mountain Venus", "Park"], ["Mountain Venus", "Dandelion Island"], ["Mountain Venus", "Success"], ["Mountain Venus", "Surf and Turf"]], "depth": 5}, "Kung Fu Panda": {"crafted_by": [["Pandamonium", "Wind"]], "depth": 7}, "Drum": {"crafted_by": [["Mire", "Woodpecker"]], "depth": 5}, "Starship": {"crafted_by": [["Steamship", "Star"], ["Steamship", "Tractor Beam"], ["Steamship", "Sea Star"], ["Star", "Helisub"], ["Star", "Bogmobile"], ["Flying Car", "Starfish"], ["Star", "Hawaiian Jet"]], "depth": 5}, "Pineapple Boat": {"crafted_by": [["Paddle", "Pineapple"]], "depth": 5}, "Sancho Panza": {"crafted_by": [["Wreck", "Don Quixote"], ["Sandal", "Don Quixote"], ["Mountain Dirt", "Don Quixote"]], "depth": 5}, "Tea Jelly": {"crafted_by": [["Tea Devil", "Jellyfish"]], "depth": 5}, "Steam Shaman": {"crafted_by": [["Steam Forest", "Shaman"]], "depth": 5}, "Fire Gnome": {"crafted_by": [["Fire", "Garden Gnome"], ["Fire Gnome", "Wind"]], "depth": 6}, "Steam Snakeboard": {"crafted_by": [["Steam Forest", "Snakeboard"]], "depth": 5}, "Teaki": {"crafted_by": [["Tea Ceremony", "Tiki Bar"]], "depth": 5}, "Creeper": {"crafted_by": [["Ghost", "Obsidian"], ["Loch Ness Monster", "Minecraft"], ["Cougher", "Creeper"], ["Fire Breath", "Minecraft"], ["Coughing", "Minecraft"], ["Coughing", "Creeper"], ["Tea Devil", "Creeper"]], "depth": 4}, "Flying Snowman": {"crafted_by": [["Flying Car", "Frosty"]], "depth": 5}, "Fighter Jet": {"crafted_by": [["Venus Flytrap", "Jet"]], "depth": 4}, "Lawrence of Arabia": {"crafted_by": [["Tea Party", "Sand Dunes"]], "depth": 4}, "Hailing": {"crafted_by": [["Coughing", "Hail"]], "depth": 5}, "Cough Captain": {"crafted_by": [["Coughing", "Captain"]], "depth": 5}, "Hermes": {"crafted_by": [["Flying Car", "Sandal"], ["Sandal", "Mountain Dirt"], ["Sandal", "Amazon"], ["Sandal", "Mountain Venus"], ["Sandal", "Nymph"], ["Sandal", "Pot of Gold"], ["Sandal", "Calliope"], ["Sandal", "Olympus Mons"], ["Sandal", "Mountain Doom"], ["Sandal", "Helijet"], ["Sandal", "Fighter Jet"], ["Sandal", "Oread"], ["Sandal", "Mountain Wine"], ["Sandal", "Yggdrasil"], ["Sandal", "Airship"], ["Sandal", "Jetpack"], ["Sandal", "Bird"], ["Sandal", "Flying"], ["Sandal", "Dragonfly"], ["Sandal", "Mercury"], ["Sandal", "Eagle"], ["Sandal", "Flying Trap"], ["Sandal", "Olympus"], ["Sandal", "Mountain Nymph"], ["Sandal", "Mountain Range"], ["Sandal", "Caduceus"], ["Sandal", "Carmaid"], ["Chinook", "Mercury"], ["Mountain Venus", "Mercury"]], "depth": 5}, "Clean Pot": {"crafted_by": [["Cleaner", "Pot"]], "depth": 5}, "Tea Clock": {"crafted_by": [["Tea Devil", "Clockwork"]], "depth": 5}, "Earl": {"crafted_by": [["Sandwich", "Prince"]], "depth": 5}, "Invention": {"crafted_by": [["Fire", "Idea"], ["Idea", "Water"]], "depth": 6}, "Space Ship": {"crafted_by": [["Boat", "Rocket"], ["Rocket", "Engine"], ["Steamship", "Milky Way"], ["Star", "Cargo"], ["Paddle", "Space Whale"], ["Paddle", "Space Fish"], ["Paddle", "Space Phoenix"], ["Paddle", "Space Tree"]], "depth": 4}, "Pain": {"crafted_by": [["Fire", "Sunburn"]], "depth": 5}, "Meteorite": {"crafted_by": [["Dragon", "Meteor"], ["Sandwich", "Meteor"], ["Ghost", "Meteor"], ["Mangrove", "Meteor"], ["Helicopter", "Meteor"], ["Lighthouse", "Meteor"], ["Volcano", "Meteor"], ["Tobacco", "Meteor"], ["Quagmire", "Meteor"], ["Beach", "Meteor"], ["Tumbleweed", "Meteor"], ["Dust Devil", "Meteor"], ["Perfume", "Meteor"], ["Boat", "Meteor"], ["Wine", "Meteor"], ["Teapot", "Meteor"], ["Mars", "Meteor"], ["Fish", "Meteor"], ["Fog", "Meteor"], ["Dust Storm", "Meteor"], ["Cinder", "Meteor"], ["Dandelion Patch", "Meteor"], ["Bee", "Meteor"], ["Meteor", "Meteor"], ["Meteor", "Tree"], ["Meteor", "Marsh"], ["Meteor", "Sky"], ["Meteor", "Tractor"], ["Meteor", "Swamp"], ["Meteor", "Stone"], ["Meteor", "Steamroller"], ["Meteor", "Buddha"], ["Meteor", "Tea"], ["Meteor", "Tea Bag"], ["Meteor", "Teacup"], ["Meteor", "Weed"], ["Meteor", "Tea Party"], ["Meteor", "Soil"], ["Meteor", "Hurricane"], ["Meteor", "Moon"], ["Meteor", "Mud"], ["Meteor", "Ship"], ["Meteor", "Desert"], ["Meteor", "Forest"], ["Meteor", "Mudweed"], ["Meteor", "Venus Flytrap"], ["Meteor", "Lake"], ["Meteor", "Train"], ["Meteor", "Lagoon"], ["Meteor", "Matcha"], ["Meteor", "Dune"], ["Meteor", "Mushroom"], ["Meteor", "Plant"], ["Meteor", "Cactus"], ["Meteor", "Whale"], ["Meteor", "Genie"], ["Meteor", "Oasis"], ["Meteor", "River"], ["Meteor", "Rock"], ["Meteor", "Water"], ["Meteor", "Kite"], ["Meteor", "Car"], ["Meteor", "Statue"], ["Meteor", "Pond"], ["Boulder", "Dust Bowl"], ["Dust Bowl", "Rock"], ["Fossil", "Space Dust"], ["Fossil", "Shooting Star"], ["Fossil", "Meteor Dew"], ["Stealth", "Meteor"], ["Tea Ceremony", "Asteroid"], ["Tea Ceremony", "Meteor"], ["Tea Ceremony", "Meteor Shower"], ["Tea Ceremony", "Comet"], ["Tea Ceremony", "Meteor Dew"], ["Party", "Meteor"], ["Salad", "Shooting Star"], ["Salad", "Meteor"], ["Salad", "Meteor Shower"], ["Earth", "Iron Wreck"], ["Earth", "Jet Wreck"], ["Earth", "Meteor Shower"], ["Earth", "Meteor Salad"], ["Earth", "Iron Sandwich"], ["Earth", "Rocky Wreck"], ["Earth", "Iron Ness"], ["Earth", "Meteor Sandwich"], ["Earth", "Meteor Dew"], ["Wreck", "Meteor"], ["Moana", "Meteor"], ["Mire", "Meteor"], ["Star", "Petrified Wood"], ["Steam Forest", "Meteor Dew"], ["Mountain Venus", "Meteor"], ["Mountain Venus", "Meteorite"], ["Mountain Dirt", "Asteroid"], ["Mountain Dirt", "Meteor"], ["Mountain Dirt", "Meteor Shower"], ["Mountain Dirt", "Comet"], ["Mountain Dirt", "Meteor Dew"]], "depth": 4}, "Dengue Fish": {"crafted_by": [["Rainbow Fish", "Dengue"]], "depth": 5}, "Glass Wreck": {"crafted_by": [["Wreck", "Glasser"]], "depth": 5}, "Seahorse": {"crafted_by": [["Dandelion", "Submarine"], ["Earth", "Sea Pony"], ["Rainbow Fish", "Stingray"]], "depth": 4}, "Coughtea": {"crafted_by": [["Coughland", "Jetea"]], "depth": 5}, "Simba": {"crafted_by": [["Lion", "Wind"], ["Moana", "Lion"]], "depth": 5}, "Offering": {"crafted_by": [["Incense", "Honey"]], "depth": 4}, "Honey Ness Monster": {"crafted_by": [["Loch Ness Monster", "Honeybee"]], "depth": 5}, "TB": {"crafted_by": [["Cougher", "Ruins"], ["Coughing", "Temple"]], "depth": 5}, "Clean Dirt": {"crafted_by": [["Mountain Dirt", "Clean Air"]], "depth": 5}, "Ophiuchus": {"crafted_by": [["Star", "Snake"]], "depth": 4}, "Star Car": {"crafted_by": [["Star", "Mountain Dewmoblie"]], "depth": 5}, "Snowland": {"crafted_by": [["Coughland", "Snowbee"]], "depth": 5}, "Matcha Moana": {"crafted_by": [["Moana", "Matcha Latte"], ["Moana", "Matcha Tea"]], "depth": 5}, "Muddy Sandal": {"crafted_by": [["Sandal", "Muddy Teacup"], ["Sandal", "Mud Tea"], ["Sandal", "Mud Puddle"], ["Sandal", "Mud Bunny"], ["Sandal", "Muddy Helicopter"]], "depth": 5}, "Mirewich": {"crafted_by": [["Sandwich", "Mire"], ["Mire", "Sandwitch"]], "depth": 5}, "Pancakes": {"crafted_by": [["Dragon", "Flattened"], ["Crepes", "Water"], ["Moana", "Flat"], ["Dragon Egg", "Flattened"]], "depth": 5}, "Love Bug": {"crafted_by": [["Flying Car", "Cupid"]], "depth": 5}, "Paddle Boat": {"crafted_by": [["Paddle", "Super Volcano"], ["Paddle", "Nether Star"], ["Paddle", "Eiffel Tower"], ["Paddle", "Wish Upon A Star"], ["Paddle", "Dandelion Tea"], ["Paddle", "Light Bulb"], ["Paddle", "Genie Trap"], ["Paddle", "Mud Geyser"]], "depth": 5}, "Steam Cleaner": {"crafted_by": [["Steam Forest", "Cleaner"], ["Steam Forest", "Dustbuster"], ["Cleaner", "Steam Train"], ["Cleaner", "Steam Rocket"]], "depth": 5}, "Tea Lizard": {"crafted_by": [["Boston Tea Party", "Lizard"]], "depth": 5}, "Lawnmower": {"crafted_by": [["Vacuum", "Tractor"], ["Tractor", "Ash"], ["Tractor", "Snake"], ["Tractor", "Flower"], ["Steamroller", "Weed"], ["Steamship", "Lawn"], ["Wreck", "Lawn"], ["Moana", "Lawn"], ["Moana", "Lawnmower"], ["Ghost", "Lawn"], ["Ghost", "Lawnmower"], ["Tea Devil", "Lawn"]], "depth": 4}, "Dune Buggy": {"crafted_by": [["Sandstorm", "Car"], ["Sand Dunes", "Car"], ["Desert", "Car"], ["Sand", "Car"], ["Dragon", "Dune Buggy"], ["Party", "Sand Buggy"], ["Boston Tea Party", "Sand Buggy"], ["Earth", "Sand Buggy"], ["Earth", "Sand Car"], ["Flying Car", "Arrakis"], ["Flying Car", "Sand Trap"], ["Flying Car", "Dune"], ["Mire", "Sand Buggy"], ["Ghost", "Sand Buggy"], ["Cougher", "Sand Buggy"], ["Chinook", "Sand Buggy"], ["Coughing", "Sand Buggy"], ["Mountain Dirt", "Sand Buggy"]], "depth": 4}, "Wednesday": {"crafted_by": [["Hump Day", "Fire"], ["Hump Day", "Water"]], "depth": 6}, "Rave": {"crafted_by": [["Party", "Cough Drop"], ["Party", "Moonlight"], ["Party", "Lighthouse"], ["Party", "Electric Eel"], ["Party", "Thunderjet"], ["Party", "Shaman"], ["Party", "Bulldozer"], ["Party", "Amber"], ["Party", "Lightning"], ["Party", "Ozymandias"], ["Party", "Lightning Bolt"], ["Party", "Surge"], ["Party", "Dustpunk"], ["Party", "Drone"], ["Party", "Kratom"], ["Party", "Dew"], ["Party", "Energy"], ["Party", "Bjork"], ["Party", "Tesla"], ["Party", "Dune"], ["Party", "Battery"], ["Party", "Forest"], ["Party", "Electric Teapot"], ["Party", "Canyon"], ["Party", "Icelandic"], ["Party", "Nirvana"], ["Party", "Giant Mushroom"], ["Party", "Enlightenment"], ["Party", "Dragonfly"], ["Party", "Dune Buggy"], ["Party", "Jellyfish"], ["Party", "Oblivion"], ["Party", "Grinder"], ["Party", "Apocalypse"], ["Party", "Cough Syrup"], ["Party", "Arrakis"], ["Party", "Electricity"], ["Party", "Car"]], "depth": 5}, "Steampunk Ice Dragon": {"crafted_by": [["Ice Dragon", "Steampunk Dandelion"]], "depth": 5}, "Coughstick": {"crafted_by": [["Coughland", "Fishstick"]], "depth": 5}, "Hangover Tea": {"crafted_by": [["Tea Devil", "Hangover"]], "depth": 5}, "Steam Table": {"crafted_by": [["Steam Forest", "Table"]], "depth": 5}, "Ice Prince": {"crafted_by": [["Ice Dragon", "Prince"]], "depth": 5}, "Salt": {"crafted_by": [["Ocean", "Ash"], ["Ghost", "Salt"], ["Eruption", "Salt"], ["Helicopter", "Salt"], ["Salt", "Fog"], ["Ash", "Sea"], ["Dust Bowl", "Sea"], ["Fossil", "Salt Lake"], ["Fossil", "Pepper"], ["Fossil", "Seasoning"], ["Fossil", "Lot\u2019s Wife"], ["Fossil", "Salty"], ["Fossil", "Brine"], ["Dragon", "Salt Lake"], ["Dragon", "Lot\u2019s Wife"], ["Dragon", "Salty Viking"], ["Dragon", "Brine"], ["Stealth", "Lot\u2019s Wife"], ["Stealth", "Saltmobile"], ["Steamship", "Salt Lake"], ["Steamship", "Lot\u2019s Wife"], ["Steamship", "Brine"], ["Tea Ceremony", "Lot\u2019s Wife"], ["Tea Ceremony", "Salty"], ["Tea Ceremony", "Saltmobile"], ["Tea Ceremony", "Brine"], ["Party", "Seasoning"], ["Party", "Brine"], ["Loch Ness Monster", "Sodium"], ["Wreck", "Lot\u2019s Wife"], ["Wreck", "Saltmobile"], ["Wreck", "Brine"], ["Salad", "Sodium"], ["Salad", "Lot\u2019s Wife"], ["Salad", "Salty"], ["Sandwich", "Sodium"], ["Fire", "Sodium Chloride"], ["Fire", "Lot\u2019s Wife"], ["Fire", "Salty"], ["Fire", "Salty Party"], ["Fire", "Saltmobile"], ["Fire", "Brine"], ["Fire", "Dead Sea"], ["Sodium Chloride", "Earth"], ["Sodium Chloride", "Wind"], ["Earth", "Vinegar"], ["Earth", "Salt Lake"], ["Earth", "Sodium"], ["Earth", "Seasoning"], ["Earth", "Lot\u2019s Wife"], ["Earth", "Salty Party"], ["Earth", "Saltmobile"], ["Earth", "Cry"], ["Earth", "Salty Viking"], ["Earth", "Brine"], ["Earth", "Utah"], ["Earth", "Dead Sea"], ["Salt Water Taffy", "Water"], ["Salt Lake", "Wind"], ["Salt Lake", "Water"], ["Sodium", "Water"], ["Lot\u2019s Wife", "Wind"], ["Lot\u2019s Wife", "Water"], ["Sweat", "Water"], ["Acid", "Water"], ["Acid", "Earth"], ["Yak Butter Tea", "Water"], ["Fossil", "Sodium"], ["Dragon", "Salty"], ["Party", "Lot\u2019s Wife"], ["Boston Tea Party", "Sodium"], ["Star", "Brine"], ["Flying Car", "Lot\u2019s Wife"], ["Flying Car", "Saltmobile"], ["Moana", "Sodium"], ["Moana", "Lot\u2019s Wife"], ["Moana", "Saltmobile"], ["Moana", "Brine"], ["Sandal", "Sodium"], ["Sandal", "Lot\u2019s Wife"], ["Mire", "Pepper"], ["Mire", "Sodium"], ["Mire", "Lot\u2019s Wife"], ["Mire", "Saltmobile"], ["Mire", "Salty Viking"], ["Dragon Egg", "Sodium"], ["Dragon Egg", "Lot\u2019s Wife"], ["Dragon Egg", "Salty"], ["Dragon Egg", "Brine"], ["Mark Twain", "Pepper"], ["Mark Twain", "Seasoning"], ["Mark Twain", "Lot\u2019s Wife"], ["Ghost", "Salt Lake"], ["Ghost", "Seasoning"], ["Ghost", "Salty"], ["Ghost", "Brine"], ["Ghost", "Dead Sea"], ["Star", "Lot\u2019s Wife"], ["Ghost", "Lot\u2019s Wife"], ["Ghost", "Sodium"], ["Paddle", "Salt Lake"], ["Paddle", "Sodium"], ["Paddle", "Seasoning"], ["Paddle", "Lot\u2019s Wife"], ["Paddle", "Brine"], ["Cougher", "Sodium"], ["Cougher", "Lot\u2019s Wife"], ["Cougher", "Dead Sea"], ["Chinook", "Lot\u2019s Wife"], ["Chinook", "Saltmobile"], ["Coughland", "Lot\u2019s Wife"], ["Coughland", "Saltmobile"], ["Coughland", "Brine"], ["Coughland", "Dead Sea"], ["Steam Forest", "Lot\u2019s Wife"], ["Steam Forest", "Brine"], ["Ice Dragon", "Sodium"], ["Ice Dragon", "Brine"], ["Fire Breath", "Salt Lake"], ["Fire Breath", "Lot\u2019s Wife"], ["Fire Breath", "Salty"], ["Fire Breath", "Saltmobile"], ["Fire Breath", "Brine"], ["Mountain Venus", "Salt Lake"], ["Mountain Venus", "Lot\u2019s Wife"], ["Mountain Venus", "Saltmobile"], ["Mountain Venus", "Salty Viking"], ["Mountain Venus", "Brine"], ["Coughing", "Sodium"], ["Coughing", "Lot\u2019s Wife"], ["Coughing", "Saltmobile"], ["Coughing", "Dead Sea"], ["Rainbow Fish", "Lot\u2019s Wife"], ["Tea Devil", "Lot\u2019s Wife"], ["Tea Devil", "Brine"], ["Mountain Dirt", "Salt Lake"], ["Mountain Dirt", "Sodium"], ["Mountain Dirt", "Lot\u2019s Wife"], ["Mountain Dirt", "Salty"], ["Mountain Dirt", "Saltmobile"], ["Mountain Dirt", "Brine"], ["Mountain Dirt", "Dead Sea"]], "depth": 3}, "Survivor": {"crafted_by": [["Surf", "Shipwreck"], ["Surfer", "Shipwreck"], ["Surfing", "Shipwreck"], ["Shipwreck", "Surfboard"], ["Wreck", "Lifeboat"], ["Wreck", "Raft"], ["Paddle", "Shipwreck"], ["Cougher", "Shipwreck"]], "depth": 4}, "Gravity": {"crafted_by": [["Fire", "Newton"]], "depth": 6}, "Fertile Soil": {"crafted_by": [["Mountain Dirt", "Compost"]], "depth": 5}, "Snowcone": {"crafted_by": [["Hawaii", "Snowman"], ["Hawaii", "Snowball"], ["Palm Tree", "Snowman"], ["Snowman", "Honey"]], "depth": 4}, "Tea Tree": {"crafted_by": [["Tree", "Tea Storm"], ["Tea Ceremony", "Treant"], ["Tea Ceremony", "Yggdrasil"], ["Boston Tea Party", "Icelandic Sandalwood"], ["Boston Tea Party", "Yggdrasil"], ["Boston Tea Party", "Sandalwood"], ["Boston Tea Party", "Lichen"], ["Tea Devil", "Space Tree"], ["Tea Devil", "Tree"], ["Tea Devil", "Treant"]], "depth": 4}, "Hacky Sack": {"crafted_by": [["Tea Ceremony", "Hack"], ["Cougher", "Palm"], ["Chinook", "Hack"]], "depth": 5}, "Egg Sandwich": {"crafted_by": [["Sandwich", "Easter Bunny"], ["Fire", "Egg Sandwich"]], "depth": 5}, "Smurfwich": {"crafted_by": [["Sandwich", "Smurf"]], "depth": 5}, "De Milo": {"crafted_by": [["Fossil", "Mountain Venus"], ["Mountain Venus", "Amber"], ["Mountain Venus", "Junk"], ["Mountain Venus", "Crack"], ["Mountain Venus", "Lawn"], ["Mountain Venus", "Light Bulb"], ["Mountain Venus", "Canyon"], ["Mountain Venus", "Cannon"], ["Mountain Venus", "Flying"], ["Mountain Venus", "Cave"], ["Mountain Venus", "Jellyfish"]], "depth": 5}, "Brinner": {"crafted_by": [["Fire", "Brunch"], ["Brinner", "Wind"], ["Brinner", "Water"]], "depth": 6}, "Lightning McQueen": {"crafted_by": [["Moana", "Yellow Car"], ["Moana", "Race Car"]], "depth": 5}, "Jeep": {"crafted_by": [["Mountain Dirt", "Amphicar"], ["Mountain Dirt", "Amphibious Car"]], "depth": 5}, "Surfing Moana": {"crafted_by": [["Moana", "Surfing Plant"]], "depth": 5}, "Pot of Gold": {"crafted_by": [["Clay", "Rainbow"], ["Weed", "Rainbow"], ["Earth", "Leprechaun"], ["Leprechaun", "Water"], ["Coughing", "Leprechaun"], ["Rainbow Fish", "Stoneware"], ["Rainbow Fish", "Clay"], ["Rainbow Fish", "Weed"], ["Rainbow Fish", "Kiln"], ["Mountain Dirt", "Leprechaun"]], "depth": 4}, "Phlegm Forest": {"crafted_by": [["Steam Forest", "Phlegm"]], "depth": 5}, "Bogey": {"crafted_by": [["Hay Fever", "Bog"]], "depth": 4}, "Scooby-Doo": {"crafted_by": [["Sandal", "Ecto-1"]], "depth": 5}, "Rally Car": {"crafted_by": [["Mountain Dirt", "Race Car"]], "depth": 5}, "Khaleesi": {"crafted_by": [["Dragon Egg", "Celebrity"], ["Ice Dragon", "Celebrity"]], "depth": 5}, "Tea Rover": {"crafted_by": [["Tea Ceremony", "Mars Rover"], ["Boston Tea Party", "Lunar Rover"], ["Boston Tea Party", "Mars Rover"], ["Tea Devil", "Lunar Rover"], ["Tea Devil", "Rover"]], "depth": 5}, "Tea Ouroboros": {"crafted_by": [["Tea Devil", "Ouroboros"]], "depth": 5}, "Moonweed": {"crafted_by": [["Moon", "Mudweed"]], "depth": 4}, "Baking": {"crafted_by": [["Coughing", "Flour"]], "depth": 5}, "Rainbow Smogroller": {"crafted_by": [["Rainbow Fish", "Smogroller"]], "depth": 5}, "Starfrog": {"crafted_by": [["Star", "Steamfrog"]], "depth": 5}, "Tantalize": {"crafted_by": [["Sandwich", "Tease"]], "depth": 5}, "Lawn Star": {"crafted_by": [["Star", "Lawnmower"]], "depth": 5}, "Biofuel": {"crafted_by": [["Fire", "Palm Oil"], ["Earth", "Palm Oil"]], "depth": 5}, "Moon Dirt": {"crafted_by": [["Mountain Dirt", "Lunar Rover"], ["Mountain Dirt", "Moon Sand"], ["Mountain Dirt", "Moon Dew"], ["Mountain Dirt", "Moon"], ["Mountain Dirt", "Moon Mountain"]], "depth": 5}, "Letter": {"crafted_by": [["Fire", "Mail"], ["Earth", "Mail"], ["Earth", "Message"]], "depth": 6}, "Kalimari": {"crafted_by": [["Wreck", "Kali"]], "depth": 5}, "Apple Pie": {"crafted_by": [["Steamship", "Apple"], ["Fire", "Apple Pie"], ["Fire", "Apple Monster"], ["Apple", "Wind"], ["Star", "Apple"], ["Chinook", "Apple"], ["Mountain Dirt", "Apple"]], "depth": 5}, "Mountain Car Venus": {"crafted_by": [["Mountain Venus", "Mountain Car"]], "depth": 5}, "Nymphomaniac": {"crafted_by": [["Nymph", "Train"], ["Wreck", "Nympho"], ["Sandwich", "Nympho"]], "depth": 4}, "Steam Norway": {"crafted_by": [["Steampunk", "Norway"]], "depth": 4}, "Fruit Ninja": {"crafted_by": [["Ninja Fruit", "Wind"]], "depth": 6}, "Sos Forest": {"crafted_by": [["Steam Forest", "SOS"]], "depth": 5}, "April 15": {"crafted_by": [["Fire", "Tax Day"]], "depth": 6}, "Brunch": {"crafted_by": [["Sandwich", "Latte"]], "depth": 5}, "Pangea": {"crafted_by": [["Chinook", "Pangaea"]], "depth": 5}, "Ice Plant": {"crafted_by": [["Glacier", "Venus Flytrap"], ["Iceberg", "Venus Flytrap"], ["Mire", "Ice Plant"], ["Ice Dragon", "Greenhouse"], ["Ice Dragon", "Prayer Plant"], ["Ice Dragon", "Helicopter Plant"], ["Ice Dragon", "Giant Venus Flytrap"], ["Ice Dragon", "Venus Flytrap"], ["Ice Dragon", "Space Plant"]], "depth": 4}, "Hot Tub": {"crafted_by": [["Party", "Geothermal"], ["Party", "Boiling Frog"], ["Party", "Hot Spring"], ["Fire", "Pool"], ["Fire", "Apres Ski"], ["Apres Ski", "Water"], ["Spa", "Water"]], "depth": 5}, "Onyx": {"crafted_by": [["Dragon", "Obsidian"], ["Earth", "Black Pearl"], ["Ghost", "Onyx"]], "depth": 4}, "Space": {"crafted_by": [["Star", "Rocket"], ["Coral", "Rocket"], ["Palm", "Rocket"], ["Poseidon", "Rocket"], ["Lily", "Rocket"], ["Wine", "Rocket"], ["Fjord", "Rocket"], ["Mars", "Rocket"], ["Fog", "Rocket"], ["Continent", "Vacuum"], ["Prayer", "Rocket"], ["Rocket", "Atlantis"], ["Rocket", "Swamp"], ["Rocket", "Fireworks"], ["Rocket", "Fairy"], ["Rocket", "Marsh"], ["Rocket", "Sky"], ["Rocket", "Weed"], ["Rocket", "Leaf"], ["Rocket", "Lake"], ["Rocket", "Forest"], ["Rocket", "Lagoon"], ["Rocket", "Plantea"], ["Rocket", "Kite"], ["Rocket", "Lotus"], ["Rocket", "Oasis"], ["Rocket", "Pond"], ["Rocket", "Kelp"], ["Moon", "Jet"], ["Vacuum", "Sky"], ["Steamship", "Nebula"], ["Tea Ceremony", "Black Hole"], ["Party", "Satellite"], ["Wreck", "Rocket"], ["Star", "Steam Rocket"], ["Star", "Dandelion Submarine"], ["Earth", "Water Rocket"], ["Loch Ness Monster", "Milky Way"], ["Star", "Mosasaurus"], ["Star", "Mountain Dew Astronaut"], ["Moana", "Astronaut"], ["Moana", "Rocket"], ["Mark Twain", "Astronaut"], ["Mark Twain", "Rocket"], ["Mire", "Rocket"], ["Coughland", "Rocket"], ["Mountain Venus", "Steam Rocket"]], "depth": 4}, "Shake": {"crafted_by": [["Earth", "Party Rock"]], "depth": 6}, "Coughth": {"crafted_by": [["Coughland", "Thoth"]], "depth": 5}, "Toasted": {"crafted_by": [["Mark Twain", "Toast"]], "depth": 5}, "Chai Dragon": {"crafted_by": [["Ice Dragon", "Chai Tea"]], "depth": 5}, "Saltpeter": {"crafted_by": [["Salt", "Geyser"], ["Salt", "Geysir"]], "depth": 4}, "Dandelion Roll Forest": {"crafted_by": [["Steam Forest", "Dandelion Roll"]], "depth": 5}, "Muddy Ness": {"crafted_by": [["Loch Ness Monster", "Mudnado"]], "depth": 5}, "Snoop Dogg": {"crafted_by": [["Mark Twain", "Stoner"], ["Mark Twain", "Cannabis"], ["Ghost", "420"]], "depth": 5}, "Captain Cough": {"crafted_by": [["Cougher", "Captain Nemo"], ["Coughing", "Captain Hook"], ["Coughing", "Captain Nemo"]], "depth": 5}, "Steam Monastery": {"crafted_by": [["Steam Forest", "Monastery"]], "depth": 5}, "Pneumonia": {"crafted_by": [["Salad", "Lung"], ["Pneumonia", "Wind"], ["Ghost", "Lung"], ["Cougher", "Lung"], ["Coughing", "Lung"], ["Coughing", "Disease"]], "depth": 5}, "Grass": {"crafted_by": [["Pokemon", "Earth"], ["Earth", "Dew"], ["Earth", "Cow"], ["Earth", "Green"], ["Earth", "Mudkipz"], ["Earth", "Pikachu"], ["Earth", "Lawn Star"], ["Earth", "Lawn"], ["Earth", "Moss"], ["Mountain Dirt", "Lawn"]], "depth": 5}, "Counterfeit": {"crafted_by": [["Cougher", "Money"]], "depth": 5}, "Portabella": {"crafted_by": [["Sandwich", "Mushroom"]], "depth": 4}, "Titanic": {"crafted_by": [["Steam", "Tsunami"], ["Helicopter", "Titanic"], ["Helicopter", "Iceberg"], ["Landslide", "Ship"], ["Landslide", "Shipwreck"], ["Lighthouse", "Steamboat"], ["Lighthouse", "Saturn"], ["Lighthouse", "Iceberg"], ["Palm", "Steamboat"], ["Tumbleweed", "Titanic"], ["Windmill", "Submarine"], ["Poseidon", "Tsunami"], ["Poseidon", "Iceberg"], ["Poseidon", "Ship"], ["Poseidon", "Shipwreck"], ["Mountain Range", "Ship"], ["Lily", "Shipwreck"], ["Perfume", "Shipwreck"], ["Boat", "Iceberg"], ["Boat", "Saturn"], ["Boat", "Disaster"], ["Earth", "Submarine"], ["Tornado", "Steamboat"], ["Nymph", "Titanic"], ["Sandstorm", "Titanic"], ["Destruction", "Submarine"], ["Destruction", "Iceberg"], ["Destruction", "Shipwreck"], ["Phoenix", "Ship"], ["Mars", "Lake"], ["Mars", "Shipwreck"], ["Himalayas", "Steamboat"], ["Himalayas", "Ocean"], ["Himalayas", "Ship"], ["Himalayas", "Shipwreck"], ["Himalayas", "Sea"], ["Blizzard", "Steamboat"], ["Snowstorm", "Steamboat"], ["Titanic", "Titanic"], ["Titanic", "Fireworks"], ["Titanic", "Steamroller"], ["Titanic", "Weed"], ["Titanic", "Mudweed"], ["Titanic", "Alligator"], ["Titanic", "Mudslide"], ["Storm", "Iceberg"], ["Storm", "Steamboat"], ["Storm", "Ship"], ["Cough", "Shipwreck"], ["Avalanche", "Steamboat"], ["Thunder", "Shipwreck"], ["Atlantis", "Iceberg"], ["Tsunami", "Submarine"], ["Tsunami", "Steamboat"], ["Tsunami", "Ship"], ["Pyramid", "Iceberg"], ["Pyramid", "Ship"], ["Pyramid", "Shipwreck"], ["Steamboat", "Iceberg"], ["Steamboat", "Hurricane"], ["Steamboat", "Earthquake"], ["Steamboat", "Disaster"], ["Steamboat", "Tempest"], ["Steamboat", "Shipwreck"], ["Meteor", "Shipwreck"], ["Iceland", "Teacup"], ["Iceland", "Shipwreck"], ["Iceland", "Tempest"], ["Submarine", "Iceberg"], ["Submarine", "Saturn"], ["Submarine", "Soil"], ["Submarine", "Hurricane"], ["Submarine", "Shipwreck"], ["Submarine", "Disaster"], ["Submarine", "Dust Bowl"], ["Submarine", "Tempest"], ["Submarine", "Brick"], ["Tractor", "Iceberg"], ["Iceberg", "Surfing"], ["Iceberg", "Tea Party"], ["Iceberg", "Saturn"], ["Iceberg", "Engine"], ["Iceberg", "Ship"], ["Iceberg", "Train"], ["Iceberg", "Whale"], ["Iceberg", "Kite"], ["Iceberg", "Shipwreck"], ["Iceberg", "Disaster"], ["Iceberg", "Surfboard"], ["Iceberg", "Lotus"], ["Iceberg", "Car"], ["Iceberg", "Brick"], ["Iceberg", "Statue"], ["Sphinx", "Shipwreck"], ["Saturn", "Lake"], ["Saturn", "Ocean"], ["Saturn", "Ship"], ["Saturn", "Whale"], ["Saturn", "Shipwreck"], ["Saturn", "Sea"], ["Steamroller", "Shipwreck"], ["Tea Party", "Shipwreck"], ["Engine", "Shipwreck"], ["Earthquake", "Ship"], ["Moon", "Shipwreck"], ["Geysir", "Ship"], ["Geysir", "Shipwreck"], ["Train", "Shipwreck"], ["Ship", "Mudslide"], ["Ship", "Disaster"], ["Shipwreck", "Mudslide"], ["Shipwreck", "Disaster"], ["Shipwreck", "Dust Bowl"], ["Fossil", "Sinking"], ["Fossil", "Sinking Ship"], ["Dragon", "Wreck"], ["Dragon", "Sinking"], ["Dragon", "Sunk"], ["Dragon", "Titan"], ["Stealth", "Love Boat"], ["Stealth", "Titanic Flytrap"], ["Steamship", "Ice Dragon"], ["Steamship", "Mountain Venus"], ["Steamship", "Eruption"], ["Steamship", "Landslide"], ["Steamship", "Saguaro"], ["Steamship", "Cupid"], ["Steamship", "Asteroid"], ["Steamship", "Banshee"], ["Steamship", "Icebot"], ["Steamship", "Lighthouse"], ["Steamship", "Abominable Snowman"], ["Steamship", "Survivor"], ["Steamship", "Neptune"], ["Steamship", "Lamp"], ["Steamship", "Sea Serpent"], ["Steamship", "Sunken"], ["Steamship", "Penguin"], ["Steamship", "Dust Island"], ["Steamship", "Eyjafjallaj\u00f6kull"], ["Steamship", "Super Volcano"], ["Steamship", "Moonwalk"], ["Steamship", "Kali"], ["Steamship", "Snowboarding"], ["Steamship", "Sinking"], ["Steamship", "Snowboarder"], ["Steamship", "Mountain Mermaid"], ["Steamship", "Hoover"], ["Steamship", "Thunderstorm"], ["Steamship", "Catastrophe"], ["Steamship", "Wipeout"], ["Steamship", "Sherpa"], ["Steamship", "Pompeii"], ["Steamship", "Paradise"], ["Steamship", "Colossus"], ["Steamship", "Siren"], ["Steamship", "Diamond"], ["Steamship", "Tornado"], ["Steamship", "Sunk"], ["Steamship", "Destruction"], ["Steamship", "Mummy"], ["Steamship", "Lifeboat"], ["Steamship", "Mirage"], ["Steamship", "Mountain Dunes"], ["Steamship", "Love Boat"], ["Steamship", "Ghostbusters"], ["Steamship", "Mountain Tempest"], ["Steamship", "Mosque"], ["Steamship", "Sinkhole"], ["Steamship", "Whirlpool"], ["Steamship", "Snowglobe"], ["Steamship", "Palm Tree"], ["Steamship", "Cherub"], ["Steamship", "Hydra"], ["Steamship", "Mosasaurus"], ["Steamship", "Rockstar"], ["Steamship", "Himalayas"], ["Steamship", "Mountain Troll"], ["Steamship", "Mountain Fairy"], ["Steamship", "Blizzard"], ["Steamship", "Alps"], ["Steamship", "Snowstorm"], ["Steamship", "Titan"], ["Steamship", "Snowbilly"], ["Steamship", "Storm"], ["Steamship", "Bogey"], ["Steamship", "Surge"], ["Steamship", "Sea Monster"], ["Steamship", "Snowball Fight"], ["Steamship", "Mountain Slide"], ["Steamship", "Carnation"], ["Steamship", "Trollboat"], ["Steamship", "Dustbin"], ["Steamship", "Snake Trap"], ["Steamship", "Idol"], ["Steamship", "Snowkite"], ["Steamship", "Avalanche"], ["Steamship", "Atlantis"], ["Steamship", "Lunar Eclipse"], ["Steamship", "Miracle"], ["Steamship", "Accident"], ["Steamship", "Troll King"], ["Steamship", "Rescue"], ["Steamship", "Cleopatra"], ["Steamship", "Wish Upon A Star"], ["Steamship", "Cinderblock"], ["Steamship", "Palm Sub"], ["Steamship", "Dustnami"], ["Steamship", "Tsunami"], ["Steamship", "Dustslide"], ["Steamship", "Surfing Sphinx"], ["Steamship", "Narcissus"], ["Steamship", "Afternoon Tea"], ["Steamship", "Constellation"], ["Steamship", "Mountain Doom"], ["Steamship", "Sink"], ["Steamship", "Snow Globe"], ["Steamship", "Snow Devil"], ["Steamship", "Tidal Wave"], ["Steamship", "Rainbow Road"], ["Steamship", "Surfer"], ["Steamship", "Mount Everest"], ["Steamship", "Champagne"], ["Steamship", "Ruins"], ["Steamship", "Sinking Ship"], ["Steamship", "Daisy"], ["Steamship", "Dust Titanic"], ["Steamship", "Snow Lotus"], ["Steamship", "Dyson"], ["Steamship", "Kraken"], ["Steamship", "Snowbird"], ["Steamship", "Sharknado"], ["Steamship", "Mountain Trap"], ["Steamship", "Phoenix Palm"], ["Steamship", "Matchito"], ["Steamship", "Lawrence of Arabia"], ["Steamship", "Tremor"], ["Steamship", "Iceberg"], ["Steamship", "Meteor Shower"], ["Steamship", "Tipsy"], ["Steamship", "Snowtrap"], ["Steamship", "Mammoth"], ["Steamship", "Matching"], ["Steamship", "Ark"], ["Steamship", "Wave"], ["Steamship", "Ice Trap"], ["Steamship", "Love"], ["Steamship", "Saturn"], ["Steamship", "Surf Bunny"], ["Steamship", "Angel of Death"], ["Steamship", "Earthquito"], ["Steamship", "David"], ["Steamship", "Wall"], ["Steamship", "Snowlord"], ["Steamship", "Hayride"], ["Steamship", "Sandtitanic"], ["Steamship", "SOS"], ["Steamship", "Hurricane"], ["Steamship", "Mirror"], ["Steamship", "Earthquake"], ["Steamship", "Snowbot"], ["Steamship", "Popsicle"], ["Steamship", "Pond Skater"], ["Steamship", "Vase"], ["Steamship", "Temple"], ["Steamship", "Snowpocalypse"], ["Steamship", "Trollface"], ["Steamship", "Blue Lagoon"], ["Steamship", "Tutankhamun"], ["Steamship", "Angel Falls"], ["Steamship", "Twister"], ["Steamship", "Steam Disaster"], ["Steamship", "Big Dipper"], ["Steamship", "Carmaid"], ["Steamship", "Caduceus"], ["Steamship", "Leviathan"], ["Steamship", "Snow Bunny"], ["Steamship", "Crystal"], ["Steamship", "Calamity"], ["Steamship", "Tears"], ["Steamship", "Everest"], ["Steamship", "Typhoon"], ["Steamship", "Earl Grey"], ["Steamship", "Ice Car"], ["Steamship", "Mountain Dew Glacier Burst"], ["Steamship", "Time Machine"], ["Steamship", "Tadpole"], ["Steamship", "Ice Angel"], ["Steamship", "Eden"], ["Steamship", "Ophiuchus"], ["Steamship", "Aurora"], ["Steamship", "Whale"], ["Steamship", "Scotland"], ["Steamship", "Polar Bear"], ["Steamship", "Teacup Storm"], ["Steamship", "Ice Snake"], ["Steamship", "Honeymoon"], ["Steamship", "Godzilla"], ["Steamship", "Snowghost"], ["Steamship", "Tide"], ["Steamship", "Snow Storm"], ["Steamship", "Success"], ["Steamship", "Celebrity"], ["Steamship", "Surf Party"], ["Steamship", "Ice Train"], ["Steamship", "Flood"], ["Steamship", "Genie"], ["Steamship", "Ice Storm"], ["Steamship", "Pluto"], ["Steamship", "Disaster"], ["Steamship", "Date"], ["Steamship", "Surfboard"], ["Steamship", "Cyclone"], ["Steamship", "Mudslide"], ["Steamship", "Snow Angel"], ["Steamship", "Wishbone"], ["Steamship", "Tempest"], ["Steamship", "Kronos"], ["Steamship", "Ice Age"], ["Steamship", "Black Lily"], ["Steamship", "Cronus"], ["Steamship", "Coffin"], ["Steamship", "Snow Phoenix"], ["Steamship", "Mountain Tsunami"], ["Steamship", "Crash"], ["Steamship", "Ruin"], ["Steamship", "Titanic Flytrap"], ["Steamship", "Shipwreck"], ["Steamship", "Myth"], ["Steamship", "Woodpecker"], ["Steamship", "Dead Sea"], ["Steamship", "Sandvik"], ["Steamship", "Titanoboa"], ["Steamship", "Titanado"], ["Steamship", "Olympus"], ["Steamship", "Matterhorn"], ["Steamship", "Mountain Genie"], ["Steamship", "Trainwreck"], ["Steamship", "Sunami"], ["Steamship", "Apocalypse"], ["Steamship", "Brick"], ["Tea Ceremony", "Sinking Ship"], ["Party", "Sinking"], ["Party", "Lifeboat"], ["Party", "Love Boat"], ["Party", "Titan"], ["Party", "Sinking Ship"], ["Party", "Iceberg"], ["Party", "Steam Disaster"], ["Party", "Shipwreck"], ["Party", "Titanado"], ["Wreck", "Hookah"], ["Wreck", "Cupid"], ["Wreck", "Banshee"], ["Wreck", "Neptune"], ["Wreck", "Tourist"], ["Wreck", "Penguin"], ["Wreck", "Candle"], ["Wreck", "Lotus Flower"], ["Wreck", "Corkscrew"], ["Wreck", "Hourglass"], ["Wreck", "Pompeii"], ["Wreck", "Paradise"], ["Wreck", "Tea Cup"], ["Wreck", "Glasses"], ["Wreck", "Colossus"], ["Wreck", "Muddy Teacup"], ["Wreck", "Teapot"], ["Wreck", "Diamond"], ["Wreck", "Farmer"], ["Wreck", "Love Boat"], ["Wreck", "Whirlpool"], ["Wreck", "Sinkhole"], ["Wreck", "Snowglobe"], ["Wreck", "Statue of Liberty"], ["Wreck", "Frost Giant"], ["Wreck", "Bridge"], ["Wreck", "Lightning"], ["Wreck", "Titan"], ["Wreck", "Golem"], ["Wreck", "Triton"], ["Wreck", "Bogey"], ["Wreck", "Lung"], ["Wreck", "Queen"], ["Wreck", "Tease"], ["Wreck", "God"], ["Wreck", "Eiffel Tower"], ["Wreck", "Balloon"], ["Wreck", "Thunder"], ["Wreck", "Atlantis"], ["Wreck", "Dust Teacup"], ["Wreck", "Cleopatra"], ["Wreck", "Afternoon Tea"], ["Wreck", "Constellation"], ["Wreck", "Ruins"], ["Wreck", "Sinking Ship"], ["Wreck", "Mountain Trap"], ["Wreck", "Lawrence of Arabia"], ["Wreck", "Iceberg"], ["Wreck", "Cruise"], ["Wreck", "Devil"], ["Wreck", "Saturn"], ["Wreck", "Cigar"], ["Wreck", "Tea Bag"], ["Wreck", "Angel of Death"], ["Wreck", "Dusty Glass"], ["Wreck", "Teacup"], ["Wreck", "Gargoyle"], ["Wreck", "Rose"], ["Wreck", "Vase"], ["Wreck", "Temple"], ["Wreck", "Africa"], ["Wreck", "Tutankhamun"], ["Wreck", "Night"], ["Wreck", "Titanicpunk"], ["Wreck", "Forest"], ["Wreck", "Tears"], ["Wreck", "Everest"], ["Wreck", "Jupiter"], ["Wreck", "Amber Venus"], ["Wreck", "Leviathan"], ["Wreck", "Steam Norway"], ["Wreck", "Zeus"], ["Wreck", "Fighter"], ["Wreck", "Whale"], ["Wreck", "Polar Bear"], ["Wreck", "Time Machine"], ["Wreck", "Onyx"], ["Wreck", "Mercury"], ["Wreck", "Umami"], ["Wreck", "Pluto"], ["Wreck", "Water Rocket"], ["Wreck", "Kronos"], ["Wreck", "Bouquet"], ["Wreck", "Titanic Flytrap"], ["Wreck", "Asia"], ["Wreck", "Statue"], ["Wreck", "Cup"], ["Wreck", "Dead Sea"], ["Wreck", "Wishbone"], ["Wreck", "Titanoboa"], ["Wreck", "Sacrifice"], ["Wreck", "Olympus"], ["Wreck", "Titanado"], ["Wreck", "Matterhorn"], ["Wreck", "Mountain Genie"], ["Wreck", "Coffin"], ["Wreck", "Ice Sculpture"], ["Boston Tea Party", "Sinking"], ["Boston Tea Party", "Sinking Ship"], ["Boston Tea Party", "Iceberg"], ["Salad", "Titanado"], ["Star", "Titanicpunk"], ["Fire", "Cruise Ship"], ["Cruise Ship", "Water"], ["Sinking", "Earth"], ["Earth", "Love Boat"], ["Earth", "Sinking Ship"], ["Earth", "Cruise"], ["Earth", "Sandtitanic"], ["Earth", "Aircraft Carrier"], ["Earth", "Titanic Flytrap"], ["Empire", "Water"], ["Hollywood", "Water"], ["Sinking Ship", "Wind"], ["Titanic Dragon", "Water"], ["Atlas", "Water"], ["Love Boat", "Water"], ["Steamship", "Party"], ["Steamship", "Wreck"], ["Steamship", "Easter"], ["Steamship", "Mountain Dew Ice"], ["Steamship", "Lily"], ["Steamship", "Snowpiercer"], ["Steamship", "Flat Glass"], ["Steamship", "Tsunamic"], ["Steamship", "Jormungandr"], ["Steamship", "Rose"], ["Steamship", "Ice Castle"], ["Steamship", "Tuberculosis"], ["Steamship", "Sting"], ["Steamship", "Brick House"], ["Steamship", "Pharaoh"], ["Wreck", "Iron"], ["Wreck", "Teabag"], ["Wreck", "Snow Globe"], ["Wreck", "Muddy Teapot"], ["Wreck", "Thunderbird"], ["Wreck", "Telescope"], ["Wreck", "Sphinx"], ["Wreck", "Tank"], ["Wreck", "Big Dipper"], ["Wreck", "Aquaman"], ["Wreck", "Earl Grey"], ["Wreck", "Scotland"], ["Wreck", "Cronus"], ["Wreck", "Crocodile"], ["Flying Car", "Titan"], ["Flying Car", "Sinking Ship"], ["Flying Car", "Iceberg"], ["Sandal", "Sinking Ship"], ["Sandal", "Titanicpunk"], ["Sandal", "Titanic Flytrap"], ["Mire", "Dust Titanic"], ["Mire", "Sinking Ship"], ["Mire", "Titanicpunk"], ["Dragon Egg", "Sinking"], ["Dragon Egg", "Sinking Ship"], ["Dragon Egg", "Dust Titanic"], ["Mark Twain", "Sinking"], ["Mark Twain", "Titan"], ["Mark Twain", "Dust Titanic"], ["Mark Twain", "Antarctica"], ["Mark Twain", "Titanic Flytrap"], ["Mark Twain", "Titanado"], ["Ghost", "Sinking"], ["Ghost", "Titan"], ["Ghost", "Titanicpunk"], ["Ghost", "Titanado"], ["Paddle", "Love Boat"], ["Mark Twain", "Iceberg"], ["Paddle", "Steam Disaster"], ["Paddle", "Titanicpunk"], ["Cougher", "Sinking"], ["Cougher", "Sunk"], ["Cougher", "Sinking Ship"], ["Cougher", "Iceberg"], ["Chinook", "Titanic Flytrap"], ["Coughland", "Sinking Ship"], ["Coughland", "Iceberg"], ["Steam Forest", "Cruise"], ["Ice Dragon", "Sunken"], ["Ice Dragon", "Sinking Ship"], ["Ice Dragon", "Sunken City"], ["Ice Dragon", "Shipwreck"], ["Ice Dragon", "Nile"], ["Fire Breath", "Titanic"], ["Fire Breath", "Sinking Ship"], ["Fire Breath", "Dust Titanic"], ["Mountain Venus", "Pirate Ship"], ["Mountain Venus", "Tea Whale"], ["Mountain Venus", "Sinking Ship"], ["Mountain Venus", "Ship"], ["Coughing", "Titan"], ["Coughing", "Sinking Ship"], ["Coughing", "Iceberg"], ["Coughing", "Shipwreck"], ["Coughing", "Titanado"], ["Rainbow Fish", "Titanicpunk"], ["Mountain Dirt", "Sinking Ship"]], "depth": 3}, "Sand Nymph": {"crafted_by": [["Sandwich", "Tea Nymph"]], "depth": 5}, "Pinkie Pie": {"crafted_by": [["Paddle", "Rainbow Dash"], ["Cleaner", "Rainbow Dash"]], "depth": 5}, "Chinok": {"crafted_by": [["Chinook", "Ruin"]], "depth": 5}, "Pudd\u2019nhead Wilson": {"crafted_by": [["Mark Twain", "Pudding"]], "depth": 5}, "Crouton": {"crafted_by": [["Salad", "Cross"], ["Cougher", "Toast"], ["Coughing", "Toast"]], "depth": 5}, "Black Knight": {"crafted_by": [["Flying Car", "Black Sand"]], "depth": 5}, "Panther": {"crafted_by": [["Sandwich", "Black"], ["Panther", "Wind"]], "depth": 5}, "Bagpipe": {"crafted_by": [["Fire", "Scotland"], ["Earth", "Kilt"], ["Earth", "Scotland"], ["Scotsman", "Earth"], ["Scotsman", "Wind"], ["Bagpipe", "Wind"], ["Ghost", "Scotland"], ["Paddle", "Scotland"], ["Chinook", "Scotland"]], "depth": 5}, "Star Station": {"crafted_by": [["Star", "Train Station"]], "depth": 5}, "Fireboat": {"crafted_by": [["Fire", "Lifeboat"], ["Fire", "Catamaran"], ["Fire", "Ferry"], ["Paddle", "Firefighter"]], "depth": 5}, "Bunny": {"crafted_by": [["Tea Ceremony", "Carrot"], ["Party", "Carrot"], ["Star", "Easter"], ["Easter", "Fire"], ["Fire", "Rabbit"], ["Fire", "Carrot"], ["Rabbit", "Water"], ["Cougher", "Easter"], ["Cleaner", "Easter"]], "depth": 5}, "Antarctica": {"crafted_by": [["Snow", "Continent"], ["Glacier", "Continent"], ["Ice", "Continent"], ["Continent", "Blizzard"], ["Continent", "Snowstorm"], ["Continent", "Snowflake"], ["Continent", "Snowmobile"], ["Continent", "Iceberg"], ["Ice Dragon", "Continent"]], "depth": 4}, "Chlorine": {"crafted_by": [["Fire", "Green"]], "depth": 5}, "Bigfoot": {"crafted_by": [["Fossil", "Yeti"], ["Loch Ness Monster", "Mountain Dirt"], ["Loch Ness Monster", "Yeti"], ["Loch Ness Monster", "Lumberjack"], ["Loch Ness Monster", "Forest Fire"], ["Loch Ness Monster", "Transcontinental Railroad"], ["Loch Ness Monster", "Campfire"], ["Loch Ness Monster", "Golem"], ["Loch Ness Monster", "Statue of Liberty"], ["Loch Ness Monster", "Dust Tree"], ["Loch Ness Monster", "Mountain Dude"], ["Loch Ness Monster", "Flat Buddha"], ["Loch Ness Monster", "Jungle"], ["Loch Ness Monster", "Rocky Mountains"], ["Loch Ness Monster", "Trees"], ["Loch Ness Monster", "Rainforest"], ["Loch Ness Monster", "Mountain Man"], ["Loch Ness Monster", "Forest"], ["Loch Ness Monster", "Haunted Tree"], ["Loch Ness Monster", "Mountain Lion"], ["Loch Ness Monster", "Moai"], ["Loch Ness Monster", "Dust Mushroom"], ["Loch Ness Monster", "Werewolf"], ["Loch Ness Monster", "Woodpecker"], ["Loch Ness Monster", "Dust Buddha"], ["Fire", "Sasquatch"], ["Earth", "Cryptid"], ["Earth", "Sasquatch"], ["Star", "Yeti"], ["Sandal", "Monster Truck"], ["Sandal", "Giant Venus Flytrap"], ["Sandal", "Ogre"], ["Sandal", "Monster"], ["Sandal", "Werewolf"], ["Mark Twain", "Yeti"], ["Mark Twain", "Monster Truck"], ["Chinook", "Mountain Mermaid"], ["Chinook", "Mountain Fairy"], ["Chinook", "Haunted Tree"], ["Chinook", "Monster"], ["Mountain Venus", "Yeti"], ["Mountain Venus", "Werewolf"], ["Mountain Dirt", "Loch Ness"], ["Mountain Dirt", "Werewolf"]], "depth": 5}, "Hula-dragon": {"crafted_by": [["Hula-Dragon", "Wind"], ["Hula-Dragon", "Water"], ["Hula-dragon", "Wind"]], "depth": 6}, "Cookie Monster": {"crafted_by": [["Cookie", "Wind"]], "depth": 7}, "Unsinkable": {"crafted_by": [["Mark Twain", "Sunk"]], "depth": 5}, "Sahara": {"crafted_by": [["Titanic", "Sand Dunes"], ["Chinook", "Africa"], ["Coughland", "Sand Dunes"]], "depth": 4}, "Airship": {"crafted_by": [["Land", "Steampunk"], ["Dandelion", "Steampunk"], ["Sky", "Steampunk"], ["Steampunk", "Ship"], ["Steampunk", "Wind"], ["Steampunk", "Kite"], ["Steampunk", "Cloud"], ["Steampunk", "Jet"], ["Steamship", "Flying Car"], ["Steamship", "Plane"], ["Steamship", "Helicoptor"], ["Steamship", "Air"], ["Steamship", "Balloon"], ["Steamship", "Airplane"], ["Steamship", "Parachute"], ["Steamship", "Pterodactyl"], ["Steamship", "Flying"], ["Steamship", "Magic Carpet"], ["Steamship", "Kite"], ["Steamship", "Hot Air Balloon"], ["Steamship", "Flying Trap"], ["Steamcactus", "Wind"], ["Stealth Castle", "Wind"], ["Steampunk Pirate", "Wind"], ["Steampunk Dragon", "Wind"], ["Steamwreck", "Wind"], ["Steam Man", "Wind"], ["Steam Tank", "Wind"], ["Steam Car", "Wind"], ["Steampunk Ship", "Wind"], ["Steampunk Glasses", "Wind"], ["Steam Punk", "Wind"], ["Kingdom", "Wind"], ["Flying Car", "Pirate Ship"], ["Flying Car", "Riverboat"], ["Flying Car", "Steampunk Pirate"], ["Flying Car", "Cattail"], ["Flying Car", "Balloon"], ["Flying Car", "Castle"], ["Flying Car", "Steamboat"], ["Flying Car", "Steam Punk"], ["Flying Car", "Cotton"], ["Flying Car", "Ship"], ["Flying Car", "Titanicpunk"], ["Flying Car", "Hot Air Balloon"], ["Flying Car", "Steampunk Dandelion"], ["Flying Car", "Anchor"], ["Mire", "Hot Air Balloon"], ["Flying Car", "Trade Winds"], ["Flying Car", "Steampunk"], ["Flying Car", "Raft"], ["Paddle", "Hot Air Balloon"]], "depth": 4}, "Lettuce": {"crafted_by": [["Salad", "Coughing"], ["Salad", "Lightbulb"], ["Salad", "Lamp"], ["Salad", "Dalai Lama"], ["Salad", "Lily"], ["Salad", "Moon Buggy"], ["Salad", "Lifeboat"], ["Salad", "Latte"], ["Salad", "Moon"], ["Salad", "Magnifying Glass"], ["Salad", "Lego"], ["Salad", "Light Bulb"], ["Salad", "Race Car"], ["Salad", "Lighthouse"]], "depth": 5}, "Carnivorous Plant": {"crafted_by": [["Land", "Venus Flytrap"], ["Fog", "Venus Flytrap"], ["Palm Tree", "Venus Flytrap"], ["Steamroller", "Venus Flytrap"], ["Earthquake", "Venus Flytrap"], ["Forest", "Venus Flytrap"], ["Venus Flytrap", "Flower"], ["Venus Flytrap", "Plant"], ["Venus Flytrap", "Pencil"], ["Venus Flytrap", "Dust Bowl"], ["Mire", "Venus Flytrap"]], "depth": 4}, "Phone": {"crafted_by": [["Telephone", "Earth"]], "depth": 7}, "Prawn": {"crafted_by": [["Earth", "Shrimp"]], "depth": 6}, "Tea Missile": {"crafted_by": [["Boston Tea Party", "Missile"], ["Tea Devil", "Missile"]], "depth": 5}, "Igloo": {"crafted_by": [["Snow", "Brick"], ["Snow", "Wood"], ["Glacier", "Brick"], ["Ice", "Island"], ["Ice", "Brick"], ["Ice", "Wood"], ["Snowstorm", "Wood"], ["Iceland", "Stone"], ["Iceland", "Brick"], ["Iceland", "Wood"], ["Snowstorm", "Brick"], ["Wreck", "Snow Fort"], ["Wreck", "Eskimo"], ["Sandwich", "Snow Fort"], ["Snow Fort", "Earth"], ["Earth", "Eskimo"], ["Mire", "Snow Fort"], ["Mire", "Eskimo"], ["Paddle", "Snow Fort"], ["Paddle", "Snow Castle"], ["Chinook", "Snow Fort"], ["Chinook", "Snow Castle"], ["Steam Forest", "Eskimo"], ["Mountain Dirt", "Eskimo"]], "depth": 4}, "Mona Lisa": {"crafted_by": [["Mountain Venus", "Glasses"], ["Mountain Venus", "Monorail"], ["Mountain Venus", "Smile"], ["Mountain Venus", "Sketch"]], "depth": 5}, "Yak Twain": {"crafted_by": [["Mark Twain", "Yak"]], "depth": 5}, "Saliva": {"crafted_by": [["Salad", "Vape"], ["Salad", "Viper"]], "depth": 5}, "Peace": {"crafted_by": [["Nobel", "Wind"], ["Nobel", "Water"], ["Chinook", "Pipe"]], "depth": 5}, "Mount Venus": {"crafted_by": [["Wreck", "Mountain Venus"], ["Mountain Venus", "Cough Drop"], ["Mountain Venus", "Anaphylaxis"], ["Mountain Venus", "Ice Cream"], ["Mountain Venus", "Marshmallow"], ["Mountain Venus", "Ghostbusters"], ["Mountain Venus", "Swat"], ["Mountain Venus", "Sandwish"], ["Mountain Venus", "Rescue"], ["Mountain Venus", "Sandwitch"], ["Mountain Venus", "Mount Everest"], ["Mountain Venus", "Champagne"], ["Mountain Venus", "Parachute"], ["Mountain Venus", "Picnic"], ["Mountain Venus", "Vacation"], ["Mountain Venus", "Smogroller"], ["Mountain Venus", "Tomb Raider"], ["Mountain Venus", "Rocky Mountains"], ["Mountain Venus", "Icecream"], ["Mountain Venus", "Subway"], ["Mountain Venus", "Table"], ["Mountain Venus", "Hot Air Balloon"], ["Mountain Venus", "Taxi"], ["Mountain Venus", "Sub"], ["Mountain Venus", "Flood"], ["Mountain Venus", "Ice Cream Sandwich"], ["Mountain Venus", "Knife"], ["Mountain Venus", "Rally"], ["Mountain Venus", "Sherry"], ["Mountain Venus", "Amber Alert"], ["Mountain Venus", "Ice Tea"]], "depth": 5}, "Mars Sandwich": {"crafted_by": [["Sandwich", "Mars Rover"]], "depth": 5}, "Vapir": {"crafted_by": [["Dragon", "Vape"]], "depth": 5}, "Flaming Martini": {"crafted_by": [["Fire Breath", "Martini"]], "depth": 5}, "Snowshoe": {"crafted_by": [["Sandal", "Snowboarding"], ["Sandal", "Snowboarder"], ["Sandal", "Snow"], ["Sandal", "Snowstorm"], ["Sandal", "Blizzard"], ["Sandal", "Snowboard"], ["Sandal", "Snowball Fight"], ["Sandal", "Snowkite"], ["Sandal", "Avalanche"], ["Sandal", "Snowbee"], ["Sandal", "Snowflake"], ["Sandal", "Snowroller"], ["Sandal", "Snow Nymph"], ["Sandal", "Snowbird"], ["Sandal", "Snowjet"], ["Sandal", "Snowtrap"], ["Sandal", "Snowman"], ["Sandal", "Snowplow"], ["Sandal", "Snowpunk"], ["Sandal", "Snowpocalypse"], ["Sandal", "Winter"], ["Sandal", "Snowdrop"], ["Sandal", "Snowmobile"], ["Sandal", "Frost"], ["Sandal", "Snow Tea"], ["Sandal", "Ski"], ["Sandal", "Snowblower"], ["Sandal", "Snowlily"], ["Paddle", "Snow"], ["Paddle", "Snowboard"], ["Sandal", "Snow Bunny"], ["Sandal", "Snowtrain"], ["Paddle", "Snowtrap"], ["Paddle", "Snowlily"]], "depth": 5}, "Taxi": {"crafted_by": [["Angel", "Car"], ["Boston Tea Party", "Chauffeur"], ["Boston Tea Party", "Yellow Car"], ["Earth", "Yellow Car"], ["Tax", "Wind"], ["Tax Day", "Wind"], ["Party", "Yellow Car"], ["Wreck", "Yellow Car"], ["Sandal", "Yellow Car"], ["Mire", "Yellow Car"], ["Paddle", "Yellow Car"], ["Cougher", "Yellow Car"], ["Coughland", "Yellow Car"], ["Coughing", "Yellow Car"], ["Tea Devil", "Chauffeur"]], "depth": 4}, "Amazonite": {"crafted_by": [["Tea Devil", "Amazon"]], "depth": 5}, "Rainbow Flytrap": {"crafted_by": [["Rainbow Fish", "Cactus Flytrap"], ["Rainbow Fish", "Saturn Flytrap"]], "depth": 5}, "Super Squirrel": {"crafted_by": [["Star", "Squirrel"]], "depth": 5}, "Skipper": {"crafted_by": [["Moana", "Skier"]], "depth": 5}, "Codpiece": {"crafted_by": [["Party", "Cod"], ["Mountain Dirt", "Cod"]], "depth": 5}, "de Milo": {"crafted_by": [["Mountain Venus", "Moonlight"], ["Mountain Venus", "Lightbulb"], ["Mountain Venus", "Lamp"], ["Mountain Venus", "Corkscrew"], ["Mountain Venus", "Drawing"], ["Mountain Venus", "Colossus"], ["Mountain Venus", "Liberty"], ["Mountain Venus", "Mirage"], ["Mountain Venus", "Balloon"], ["Mountain Venus", "Ceramic"], ["Mountain Venus", "Glass"], ["Mountain Venus", "Clay"], ["Mountain Venus", "Eraser"], ["Mountain Venus", "Mirror"], ["Mountain Venus", "Adobe"], ["Mountain Venus", "Crystal"], ["Mountain Venus", "Lens"], ["Mountain Venus", "Art"], ["Mountain Venus", "Brick"]], "depth": 5}, "Ninja Fish": {"crafted_by": [["Stealth", "Aquarium"], ["Stealth", "Fishbowl"]], "depth": 5}}