{"Kite": {"crafted_by": [["Wind", "Seaweed"], ["Wind", "Tea"], ["Pencil", "Wind"], ["Wind", "Weed"], ["Wind", "Rocket"], ["Wind", "Matcha"], ["Wind", "Tea Bag"], ["Wind", "Surfer"], ["Wind", "Surfboard"], ["Wind", "Buddha"], ["Wind", "Surfing"], ["Cough", "Kite"], ["Nothing", "Kite"], ["Oasis", "Kite"]], "depth": 3}, "Leaf": {"crafted_by": [["Wind", "Tree"]], "depth": 3}, "Lava": {"crafted_by": [["Fire", "Earth"], ["Fire", "Volcano"], ["Wave", "Volcano"], ["Volcano", "Mountain"], ["Volcano", "Plant"], ["Volcano", "Steam"], ["Volcano", "Water"], ["Volcano", "Earth"], ["Fire", "Stone"], ["Tea", "Volcano"], ["Volcano", "Tree"], ["Volcano", "Eruption"], ["Volcano", "Mud"], ["Volcano", "Stone"], ["Volcano", "Swamp"], ["Volcano", "Ash"], ["Volcano", "Lily"], ["Eruption", "Water"], ["Steamroller", "Volcano"], ["Land", "Volcano"], ["Pencil", "Volcano"], ["Amber", "Volcano"], ["Fire", "Obsidian"], ["Geysir", "Buddha"], ["Hawaii", "Tumbleweed"], ["Hawaii", "Desert"], ["Hawaii", "Volcano"], ["Hawaii", "Bog"], ["Hawaii", "Buddha"], ["Sun", "Volcano"], ["Sun", "Eruption"], ["Destruction", "Volcano"], ["Cough", "Rock"], ["Palm", "Volcano"], ["Yellowstone", "Surfer"], ["Forest", "Volcano"], ["Marsh", "Volcano"], ["Weed", "Volcano"], ["Weed", "Eruption"], ["Smog", "Volcano"], ["Snake", "Volcano"], ["Iceland", "Mud"], ["Car", "Volcano"], ["Volcano", "Chai"], ["Volcano", "Cinder"], ["Volcano", "Flower"], ["Volcano", "Nothing"], ["Volcano", "Train"], ["Volcano", "Surfer"], ["Volcano", "Mudslide"], ["Volcano", "Lotus"], ["Volcano", "Ghost"], ["Volcano", "Boat"], ["Volcano", "Buddha"], ["Volcano", "Soil"], ["Volcano", "Cactus"], ["Eruption", "Cactus"], ["Eruption", "Frog"], ["Eruption", "Buddha"]], "depth": 1}}