{"Cthulhu": {"crafted_by": [["Party", "Leviathan"], ["Loch Ness Monster", "Medusa"], ["Loch Ness Monster", "Crab"], ["Loch Ness Monster", "Thoth"], ["Loch Ness Monster", "Satan"], ["Loch Ness Monster", "Nether Star"], ["Loch Ness Monster", "Minotaur"], ["Loch Ness Monster", "Black Hole"], ["Loch Ness Monster", "Anaconda"], ["Loch Ness Monster", "Kraken"], ["Loch Ness Monster", "Sphinx"], ["Loch Ness Monster", "Trollface"], ["Loch Ness Monster", "Leviathan"], ["Loch Ness Monster", "Dust Tea Devil"], ["Loch Ness Monster", "Yin Yang"], ["Loch Ness Monster", "Troll"], ["Loch Ness Monster", "Godzilla"], ["Loch Ness Monster", "Kronos"], ["Loch Ness Monster", "Troll 2"]], "depth": 5}, "Nutty Revolution": {"discovered": false, "emoji": "\ud83e\udd5c\ud83d\udd25\ud83c\udf0e", "depth": 5}}