{"Coffinland": {"discovered": false, "emoji": "\u26b0\ufe0f\ud83c\udfde\ufe0f", "depth": 5}, "Guns N\u2019 Roses": {"discovered": false, "emoji": "\ud83c\udfb8", "depth": 5}, "Hare": {"discovered": false, "emoji": "\ud83d\udc07", "depth": 6}, "Throat": {"discovered": false, "emoji": "\ud83d\udca6", "depth": 4}, "Frog": {"discovered": false, "emoji": "\ud83d\udc38", "depth": 3}, "Hump Day": {"discovered": false, "emoji": "\ud83d\udc2a", "depth": 5}, "Captain Tea": {"discovered": false, "emoji": "\u2615\ufe0f", "depth": 5}, "Carpenter": {"discovered": false, "emoji": "\ud83d\udd28", "depth": 4}, "Falling Dragon": {"discovered": false, "emoji": "\ud83d\udc09", "depth": 5}, "Cubana": {"discovered": false, "emoji": "\ud83c\udde8\ud83c\uddfa", "depth": 5}, "Boa": {"discovered": false, "emoji": "\ud83d\udc0d", "depth": 5}, "Shamu": {"discovered": false, "emoji": "\ud83d\udc33", "depth": 5}, "Scotsman": {"discovered": false, "emoji": "\ud83c\udff4\udb40\udc67\udb40\udc62", "depth": 6}, "Smoketwain": {"discovered": false, "emoji": "\ud83d\udeac", "depth": 5}, "Lucifer": {"discovered": false, "emoji": "\ud83d\ude08", "depth": 5}, "Space Jam": {"discovered": false, "emoji": "\ud83c\udfc0", "depth": 5}, "Party Dash": {"discovered": false, "emoji": "\ud83d\udc83", "depth": 5}, "Deviled Egg": {"discovered": false, "emoji": "\ud83e\udd5a", "depth": 5}, "Moana 2": {"discovered": false, "emoji": "\ud83c\udf0a\ud83c\udf3a\ud83d\udea3", "depth": 5}, "Choke": {"discovered": false, "emoji": "\ud83d\ude35", "depth": 4}, "Space Tea Ceremony": {"discovered": false, "emoji": "\ud83d\ude80\ud83c\udf75", "depth": 5}, "Scope": {"discovered": false, "emoji": "\ud83d\udd2d", "depth": 5}, "Oolong Tea": {"discovered": false, "emoji": "\ud83c\udf75", "depth": 5}, "Sunstroke": {"discovered": false, "emoji": "\ud83c\udf1e", "depth": 4}, "Surf Bowl": {"discovered": false, "emoji": "\ud83c\udfc4", "depth": 4}, "Everglades": {"discovered": false, "emoji": "\ud83d\udc0a", "depth": 4}, "Bermuda Triangle": {"discovered": false, "emoji": "\ud83c\udf0a", "depth": 5}, "Whooping Crane": {"discovered": false, "emoji": "\ud83e\udda4", "depth": 5}, "Lunar Rover": {"discovered": false, "emoji": "\ud83c\udf12", "depth": 4}, "Snow White": {"discovered": false, "emoji": "\ud83c\udf4e", "depth": 4}, "Continent": {"discovered": false, "emoji": "\ud83c\udf0e", "depth": 3}, "Mammoth Dragon": {"discovered": false, "emoji": "\ud83d\udc09", "depth": 5}, "Titan": {"discovered": false, "emoji": "\ud83c\udf0e", "depth": 4}, "Great Wall Of Cough": {"discovered": false, "emoji": "\ud83e\udd27\ud83c\udfef", "depth": 5}, "Solar Forest": {"discovered": false, "emoji": "\ud83c\udf33", "depth": 5}, "Paddlepunk": {"discovered": false, "emoji": "\ud83d\udef6", "depth": 5}, "Snow Whale": {"discovered": false, "emoji": "\ud83d\udc0b", "depth": 4}, "Peanut Butter And Jellyfish": {"discovered": false, "emoji": "\ud83e\udd5c\ud83c\udf47\ud83d\udc1f", "depth": 6}, "Aloe Forest": {"discovered": false, "emoji": "\ud83c\udf3f", "depth": 5}, "Hot Water": {"discovered": false, "emoji": "\ud83c\udf21\ufe0f", "depth": 5}, "Tea Mantis": {"discovered": false, "emoji": "\ud83c\udf75", "depth": 5}, "Surfing Sphinx": {"discovered": false, "emoji": "\ud83c\udfdc\ufe0f", "depth": 4}, "Yellow Tea": {"discovered": false, "emoji": "\ud83c\udf75", "depth": 4}, "Flying Snakeboarder": {"discovered": false, "emoji": "\ud83d\udc0d\ud83d\udef9\u2708\ufe0f", "depth": 5}, "Catwreck": {"discovered": false, "emoji": "\ud83d\udc08", "depth": 5}, "Woodcutter": {"discovered": false, "emoji": "\ud83e\ude93", "depth": 5}, "Margarita": {"discovered": false, "emoji": "\ud83c\udf79", "depth": 5}, "Sundae": {"discovered": false, "emoji": "\ud83c\udf68", "depth": 5}, "Snowbird": {"discovered": false, "emoji": "\ud83e\udd85", "depth": 4}, "Frisbee": {"discovered": false, "emoji": "\ud83e\udd4f", "depth": 5}, "Snow Helicopter": {"discovered": false, "emoji": "\u2744\ufe0f", "depth": 4}, "Fireworks": {"discovered": false, "emoji": "\ud83c\udf86", "depth": 3}, "Coughing Tea Bagger": {"discovered": false, "emoji": "\ud83e\udd27\ud83c\udf75", "depth": 5}, "Noah\u2019s Ark": {"discovered": false, "emoji": "\ud83d\udc18", "depth": 5}, "Burns": {"discovered": false, "emoji": "\ud83d\udd25", "depth": 6}, "Rebirth": {"discovered": false, "emoji": "\ud83c\udf31", "depth": 4}, "Sandwich Angel": {"discovered": false, "emoji": "\ud83e\udd6a", "depth": 5}, "Dragon Kite": {"discovered": false, "emoji": "\ud83e\ude81", "depth": 5}, "Fire Viking": {"discovered": false, "emoji": "\ud83d\udd25", "depth": 6}, "Troll Forest": {"discovered": false, "emoji": "\ud83c\udf32\ud83d\udc79\ud83c\udf32", "depth": 5}, "T-Rex": {"discovered": false, "emoji": "\ud83e\udd96", "depth": 4}, "Ben Franklin": {"discovered": false, "emoji": "\ud83d\udca1", "depth": 5}, "Flying Carpet": {"discovered": false, "emoji": "\ud83e\ude83", "depth": 5}, "Coughing Mantis": {"discovered": false, "emoji": "\ud83e\udd97", "depth": 5}, "Rainbow Palm": {"discovered": false, "emoji": "\ud83c\udf08\ud83c\udf34", "depth": 5}, "Steam Fever": {"discovered": false, "emoji": "\ud83d\udca6", "depth": 4}, "Risotto": {"discovered": false, "emoji": "\ud83c\udf5a", "depth": 5}, "Tea Lara": {"discovered": false, "emoji": "\ud83c\udf75", "depth": 5}, "Frozen Frog": {"discovered": false, "emoji": "\ud83d\udc38", "depth": 5}, "Clean Teapot": {"discovered": false, "emoji": "\ud83e\uded6", "depth": 4}, "Stardew": {"discovered": false, "emoji": "\ud83c\udf3e", "depth": 5}, "Quarry": {"discovered": false, "emoji": "\ud83d\udd28", "depth": 4}, "Pink Tea Party": {"discovered": false, "emoji": "\ud83c\udf80\ud83c\udf75\ud83c\udf89", "depth": 5}, "Catnado": {"discovered": false, "emoji": "\ud83d\udc31\ud83c\udf2a\ufe0f", "depth": 5}, "Ambulance": {"discovered": false, "emoji": "\ud83d\ude91", "depth": 5}, "Cough Monster": {"discovered": false, "emoji": "\ud83e\udd27\ud83d\udc79", "depth": 5}, "Flying Dustbuster": {"discovered": false, "emoji": "\ud83e\uddf9", "depth": 5}, "Tea Surfing": {"discovered": false, "emoji": "\ud83c\udf75", "depth": 4}, "Loch Ness Sandwich": {"discovered": false, "emoji": "\ud83e\udd95\ud83e\udd6a", "depth": 5}, "Moby Dick": {"discovered": false, "emoji": "\ud83d\udc33", "depth": 4}, "Sushi Chef": {"discovered": false, "emoji": "\ud83c\udf63", "depth": 5}, "Lagoon": {"discovered": false, "emoji": "\ud83c\udf0a", "depth": 3}, "Owl": {"discovered": false, "emoji": "\ud83e\udd89", "depth": 4}, "Apple Monster": {"discovered": false, "emoji": "\ud83c\udf4e", "depth": 5}, "Star Surf": {"discovered": false, "emoji": "\ud83c\udfc4\u200d\u2642\ufe0f", "depth": 5}, "The King of Broken Dreams": {"discovered": false, "emoji": "\ud83d\udc51\ud83d\udc94", "depth": 5}, "Aphrodite": {"discovered": false, "emoji": "\ud83d\udc98", "depth": 4}, "Ice Angel": {"discovered": false, "emoji": "\u2744\ufe0f", "depth": 4}, "Piggy Bank": {"discovered": false, "emoji": "\ud83d\udcb0", "depth": 5}, "Mistletoe": {"discovered": false, "emoji": "\ud83c\udf84", "depth": 5}, "Sponge Cough": {"discovered": false, "emoji": "\ud83e\uddfd\ud83e\udd27", "depth": 5}, "Gorgon": {"discovered": false, "emoji": "\ud83d\udc0d", "depth": 5}, "Tea Rocket": {"discovered": false, "emoji": "\ud83d\ude80", "depth": 5}, "Wedding": {"discovered": false, "emoji": "\ud83d\udc70", "depth": 5}, "River": {"discovered": false, "emoji": "\ud83c\udf0a", "depth": 3}, "Harry Potter": {"discovered": false, "emoji": "\ud83e\uddd9\u200d\u2642\ufe0f", "depth": 5}, "Bubble": {"discovered": false, "emoji": "\ud83d\udcac", "depth": 5}, "Seraph Forest": {"discovered": false, "emoji": "\ud83c\udf33", "depth": 5}, "Climax": {"discovered": false, "emoji": "\ud83d\udca6", "depth": 5}, "Skateboard": {"discovered": false, "emoji": "\ud83d\udef9", "depth": 4}, "Stargazing": {"discovered": false, "emoji": "\ud83c\udf0c", "depth": 5}, "Genie": {"discovered": false, "emoji": "\ud83e\uddde\u200d\u2642\ufe0f", "depth": 3}, "Ice Storm": {"discovered": false, "emoji": "\u2744\ufe0f", "depth": 4}, "Castro": {"discovered": false, "emoji": "\ud83c\udf99\ufe0f", "depth": 5}, "Stealth Jet": {"discovered": false, "emoji": "\ud83d\udef8", "depth": 5}, "Warship": {"discovered": false, "emoji": "\u2693\ufe0f", "depth": 5}, "Old Faithful": {"discovered": false, "emoji": "\ud83c\udf0b", "depth": 4}, "Chocolate Tea": {"discovered": false, "emoji": "\ud83c\udf6b", "depth": 5}, "Flying Coughland": {"discovered": false, "emoji": "\u2708\ufe0f\ud83e\udd27", "depth": 5}, "Steam Kiteweed": {"discovered": false, "emoji": "\ud83c\udf3f", "depth": 5}, "Mountain Bike": {"discovered": false, "emoji": "\ud83d\udeb5", "depth": 5}, "Screwdriver": {"discovered": false, "emoji": "\ud83d\udd27", "depth": 5}, "Wheeze": {"discovered": false, "emoji": "\ud83e\udd27", "depth": 5}, "Detergent": {"discovered": false, "emoji": "\ud83e\uddfc", "depth": 5}, "Steam Beacon": {"discovered": false, "emoji": "\ud83d\udcab", "depth": 5}, "Smoking": {"discovered": false, "emoji": "\ud83d\udeac", "depth": 4}, "Rainbow Viking": {"discovered": false, "emoji": "\ud83c\udf08", "depth": 5}, "Teacup Rainbow Fish": {"discovered": false, "emoji": "\ud83d\udc20", "depth": 5}}