{"Buzz": {"crafted_by": [["Bee", "Mosquito"], ["Bee", "Mountain Dew"], ["Mosquito", "Pencil"], ["Mosquito", "Weed"]], "depth": 4}, "Crab": {"crafted_by": [["Dune", "Seaweed"], ["Sea", "Mangrove"], ["Sand Dunes", "Coral"], ["Palm Tree", "Sushi"], ["Sandtitanic", "Crab"]], "depth": 4}, "Dirt": {"crafted_by": [["Sandwich", "Soil"], ["Sandwich", "Earth"], ["Dust", "Mudweed"], ["Kite", "Earth"], ["Smell", "Muddy Cough"]], "depth": 4}, "Eden": {"crafted_by": [["Oasis", "Venus"], ["Plantea", "Angel"]], "depth": 4}, "Cool": {"crafted_by": [["Smell", "Menthol"]], "depth": 6}, "Cook": {"crafted_by": [["Smell", "Pot"], ["Smell", "Chef"], ["Sandtitanic", "Chef"]], "depth": 5}, "Corn": {"crafted_by": [["Seed", "Tractor"], ["Sandtitanic", "Corn"]], "depth": 4}}